<annotation>
	<folder></folder>
	<filename>1_DALL-E-2022-11-28-12-43-44_png.rf.5e9c8999dbd77b859be661e8c1e73259.jpg</filename>
	<path>1_DALL-E-2022-11-28-12-43-44_png.rf.5e9c8999dbd77b859be661e8c1e73259.jpg</path>
	<source>
		<database>roboflow.com</database>
	</source>
	<size>
		<width>1024</width>
		<height>1024</height>
		<depth>3</depth>
	</size>
	<segmented>0</segmented>
	<object>
		<name>bloodstain</name>
		<pose>Unspecified</pose>
		<truncated>0</truncated>
		<difficult>0</difficult>
		<occluded>0</occluded>
		<bndbox>
			<xmin>477</xmin>
			<xmax>810</xmax>
			<ymin>406</ymin>
			<ymax>711</ymax>
		</bndbox>
		<polygon>
			<x1>682</x1>
			<y1>406</y1>
			<x2>681</x2>
			<y2>407</y2>
			<x3>668</x3>
			<y3>407</y3>
			<x4>667</x4>
			<y4>406</y4>
			<x5>658</x5>
			<y5>406</y5>
			<x6>657</x6>
			<y6>407</y6>
			<x7>658</x7>
			<y7>408</y7>
			<x8>658</x8>
			<y8>409</y8>
			<x9>659</x9>
			<y9>410</y9>
			<x10>659</x10>
			<y10>412</y10>
			<x11>660</x11>
			<y11>413</y11>
			<x12>658</x12>
			<y12>415</y12>
			<x13>657</x13>
			<y13>415</y13>
			<x14>656</x14>
			<y14>416</y14>
			<x15>655</x15>
			<y15>416</y15>
			<x16>654</x16>
			<y16>417</y16>
			<x17>649</x17>
			<y17>417</y17>
			<x18>648</x18>
			<y18>416</y18>
			<x19>647</x19>
			<y19>416</y19>
			<x20>646</x20>
			<y20>415</y20>
			<x21>644</x21>
			<y21>417</y21>
			<x22>643</x22>
			<y22>417</y22>
			<x23>640</x23>
			<y23>420</y23>
			<x24>634</x24>
			<y24>420</y24>
			<x25>633</x25>
			<y25>419</y25>
			<x26>630</x26>
			<y26>419</y26>
			<x27>629</x27>
			<y27>418</y27>
			<x28>627</x28>
			<y28>418</y28>
			<x29>626</x29>
			<y29>417</y29>
			<x30>624</x30>
			<y30>417</y30>
			<x31>623</x31>
			<y31>416</y31>
			<x32>622</x32>
			<y32>416</y32>
			<x33>621</x33>
			<y33>415</y33>
			<x34>615</x34>
			<y34>415</y34>
			<x35>614</x35>
			<y35>414</y35>
			<x36>610</x36>
			<y36>414</y36>
			<x37>609</x37>
			<y37>415</y37>
			<x38>606</x38>
			<y38>415</y38>
			<x39>605</x39>
			<y39>416</y39>
			<x40>602</x40>
			<y40>416</y40>
			<x41>601</x41>
			<y41>417</y41>
			<x42>593</x42>
			<y42>417</y42>
			<x43>592</x43>
			<y43>416</y43>
			<x44>587</x44>
			<y44>416</y44>
			<x45>586</x45>
			<y45>417</y45>
			<x46>585</x46>
			<y46>417</y46>
			<x47>583</x47>
			<y47>419</y47>
			<x48>582</x48>
			<y48>419</y48>
			<x49>580</x49>
			<y49>421</y49>
			<x50>579</x50>
			<y50>421</y50>
			<x51>577</x51>
			<y51>423</y51>
			<x52>576</x52>
			<y52>423</y52>
			<x53>574</x53>
			<y53>425</y53>
			<x54>573</x54>
			<y54>425</y54>
			<x55>572</x55>
			<y55>426</y55>
			<x56>571</x56>
			<y56>426</y56>
			<x57>570</x57>
			<y57>427</y57>
			<x58>569</x58>
			<y58>427</y58>
			<x59>568</x59>
			<y59>428</y59>
			<x60>567</x60>
			<y60>428</y60>
			<x61>566</x61>
			<y61>429</y61>
			<x62>565</x62>
			<y62>429</y62>
			<x63>564</x63>
			<y63>430</y63>
			<x64>563</x64>
			<y64>430</y64>
			<x65>562</x65>
			<y65>431</y65>
			<x66>561</x66>
			<y66>431</y66>
			<x67>560</x67>
			<y67>432</y67>
			<x68>559</x68>
			<y68>432</y68>
			<x69>558</x69>
			<y69>433</y69>
			<x70>557</x70>
			<y70>433</y70>
			<x71>555</x71>
			<y71>435</y71>
			<x72>554</x72>
			<y72>435</y72>
			<x73>553</x73>
			<y73>436</y73>
			<x74>552</x74>
			<y74>436</y74>
			<x75>551</x75>
			<y75>437</y75>
			<x76>550</x76>
			<y76>437</y76>
			<x77>549</x77>
			<y77>438</y77>
			<x78>548</x78>
			<y78>438</y78>
			<x79>547</x79>
			<y79>439</y79>
			<x80>546</x80>
			<y80>439</y80>
			<x81>544</x81>
			<y81>441</y81>
			<x82>544</x82>
			<y82>442</y82>
			<x83>543</x83>
			<y83>443</y83>
			<x84>543</x84>
			<y84>444</y84>
			<x85>542</x85>
			<y85>445</y85>
			<x86>542</x86>
			<y86>446</y86>
			<x87>541</x87>
			<y87>447</y87>
			<x88>541</x88>
			<y88>448</y88>
			<x89>540</x89>
			<y89>449</y89>
			<x90>540</x90>
			<y90>450</y90>
			<x91>539</x91>
			<y91>451</y91>
			<x92>539</x92>
			<y92>452</y92>
			<x93>538</x93>
			<y93>453</y93>
			<x94>538</x94>
			<y94>454</y94>
			<x95>537</x95>
			<y95>455</y95>
			<x96>537</x96>
			<y96>458</y96>
			<x97>536</x97>
			<y97>459</y97>
			<x98>536</x98>
			<y98>461</y98>
			<x99>535</x99>
			<y99>462</y99>
			<x100>535</x100>
			<y100>468</y100>
			<x101>534</x101>
			<y101>469</y101>
			<x102>534</x102>
			<y102>472</y102>
			<x103>535</x103>
			<y103>473</y103>
			<x104>534</x104>
			<y104>474</y104>
			<x105>534</x105>
			<y105>475</y105>
			<x106>535</x106>
			<y106>476</y106>
			<x107>535</x107>
			<y107>478</y107>
			<x108>533</x108>
			<y108>480</y108>
			<x109>512</x109>
			<y109>480</y109>
			<x110>511</x110>
			<y110>481</y110>
			<x111>498</x111>
			<y111>481</y111>
			<x112>497</x112>
			<y112>482</y112>
			<x113>491</x113>
			<y113>482</y113>
			<x114>490</x114>
			<y114>483</y114>
			<x115>490</x115>
			<y115>486</y115>
			<x116>489</x116>
			<y116>487</y116>
			<x117>487</x117>
			<y117>487</y117>
			<x118>486</x118>
			<y118>486</y118>
			<x119>484</x119>
			<y119>486</y119>
			<x120>482</x120>
			<y120>484</y120>
			<x121>481</x121>
			<y121>484</y121>
			<x122>480</x122>
			<y122>483</y122>
			<x123>476</x123>
			<y123>483</y123>
			<x124>476</x124>
			<y124>486</y124>
			<x125>477</x125>
			<y125>487</y125>
			<x126>477</x126>
			<y126>488</y126>
			<x127>479</x127>
			<y127>490</y127>
			<x128>480</x128>
			<y128>490</y128>
			<x129>482</x129>
			<y129>492</y129>
			<x130>483</x130>
			<y130>492</y130>
			<x131>484</x131>
			<y131>493</y131>
			<x132>487</x132>
			<y132>493</y132>
			<x133>488</x133>
			<y133>494</y133>
			<x134>491</x134>
			<y134>494</y134>
			<x135>494</x135>
			<y135>497</y135>
			<x136>495</x136>
			<y136>497</y136>
			<x137>497</x137>
			<y137>499</y137>
			<x138>496</x138>
			<y138>500</y138>
			<x139>496</x139>
			<y139>501</y139>
			<x140>495</x140>
			<y140>502</y140>
			<x141>495</x141>
			<y141>503</y141>
			<x142>493</x142>
			<y142>505</y142>
			<x143>493</x143>
			<y143>506</y143>
			<x144>490</x144>
			<y144>509</y144>
			<x145>490</x145>
			<y145>510</y145>
			<x146>488</x146>
			<y146>512</y146>
			<x147>488</x147>
			<y147>513</y147>
			<x148>487</x148>
			<y148>514</y148>
			<x149>487</x149>
			<y149>516</y149>
			<x150>486</x150>
			<y150>517</y150>
			<x151>486</x151>
			<y151>521</y151>
			<x152>485</x152>
			<y152>522</y152>
			<x153>485</x153>
			<y153>523</y153>
			<x154>486</x154>
			<y154>524</y154>
			<x155>485</x155>
			<y155>525</y155>
			<x156>485</x156>
			<y156>529</y156>
			<x157>486</x157>
			<y157>530</y157>
			<x158>486</x158>
			<y158>538</y158>
			<x159>487</x159>
			<y159>539</y159>
			<x160>487</x160>
			<y160>544</y160>
			<x161>488</x161>
			<y161>545</y161>
			<x162>488</x162>
			<y162>550</y162>
			<x163>489</x163>
			<y163>551</y163>
			<x164>489</x164>
			<y164>556</y164>
			<x165>490</x165>
			<y165>557</y165>
			<x166>490</x166>
			<y166>561</y166>
			<x167>491</x167>
			<y167>562</y167>
			<x168>491</x168>
			<y168>566</y168>
			<x169>492</x169>
			<y169>567</y169>
			<x170>492</x170>
			<y170>571</y170>
			<x171>493</x171>
			<y171>572</y171>
			<x172>493</x172>
			<y172>575</y172>
			<x173>494</x173>
			<y173>576</y173>
			<x174>494</x174>
			<y174>577</y174>
			<x175>495</x175>
			<y175>578</y175>
			<x176>495</x176>
			<y176>580</y176>
			<x177>496</x177>
			<y177>581</y177>
			<x178>496</x178>
			<y178>583</y178>
			<x179>497</x179>
			<y179>584</y179>
			<x180>497</x180>
			<y180>585</y180>
			<x181>498</x181>
			<y181>586</y181>
			<x182>498</x182>
			<y182>587</y182>
			<x183>500</x183>
			<y183>589</y183>
			<x184>500</x184>
			<y184>590</y184>
			<x185>508</x185>
			<y185>598</y185>
			<x186>509</x186>
			<y186>598</y186>
			<x187>513</x187>
			<y187>602</y187>
			<x188>513</x188>
			<y188>608</y188>
			<x189>514</x189>
			<y189>609</y189>
			<x190>514</x190>
			<y190>616</y190>
			<x191>516</x191>
			<y191>618</y191>
			<x192>516</x192>
			<y192>619</y192>
			<x193>518</x193>
			<y193>621</y193>
			<x194>524</x194>
			<y194>621</y194>
			<x195>525</x195>
			<y195>622</y195>
			<x196>531</x196>
			<y196>622</y196>
			<x197>532</x197>
			<y197>623</y197>
			<x198>536</x198>
			<y198>623</y198>
			<x199>537</x199>
			<y199>624</y199>
			<x200>541</x200>
			<y200>624</y200>
			<x201>542</x201>
			<y201>625</y201>
			<x202>543</x202>
			<y202>625</y202>
			<x203>545</x203>
			<y203>627</y203>
			<x204>545</x204>
			<y204>630</y204>
			<x205>546</x205>
			<y205>631</y205>
			<x206>546</x206>
			<y206>633</y206>
			<x207>547</x207>
			<y207>634</y207>
			<x208>547</x208>
			<y208>637</y208>
			<x209>548</x209>
			<y209>638</y209>
			<x210>548</x210>
			<y210>640</y210>
			<x211>549</x211>
			<y211>641</y211>
			<x212>549</x212>
			<y212>644</y212>
			<x213>550</x213>
			<y213>645</y213>
			<x214>550</x214>
			<y214>647</y214>
			<x215>551</x215>
			<y215>648</y215>
			<x216>551</x216>
			<y216>649</y216>
			<x217>552</x217>
			<y217>650</y217>
			<x218>552</x218>
			<y218>652</y218>
			<x219>553</x219>
			<y219>653</y219>
			<x220>553</x220>
			<y220>655</y220>
			<x221>554</x221>
			<y221>656</y221>
			<x222>554</x222>
			<y222>657</y222>
			<x223>555</x223>
			<y223>658</y223>
			<x224>555</x224>
			<y224>659</y224>
			<x225>564</x225>
			<y225>668</y225>
			<x226>565</x226>
			<y226>668</y226>
			<x227>566</x227>
			<y227>669</y227>
			<x228>567</x228>
			<y228>669</y228>
			<x229>568</x229>
			<y229>670</y229>
			<x230>570</x230>
			<y230>670</y230>
			<x231>571</x231>
			<y231>671</y231>
			<x232>572</x232>
			<y232>671</y232>
			<x233>573</x233>
			<y233>672</y233>
			<x234>580</x234>
			<y234>672</y234>
			<x235>581</x235>
			<y235>671</y235>
			<x236>591</x236>
			<y236>671</y236>
			<x237>592</x237>
			<y237>672</y237>
			<x238>594</x238>
			<y238>672</y238>
			<x239>595</x239>
			<y239>673</y239>
			<x240>597</x240>
			<y240>673</y240>
			<x241>598</x241>
			<y241>674</y241>
			<x242>599</x242>
			<y242>674</y242>
			<x243>600</x243>
			<y243>675</y243>
			<x244>602</x244>
			<y244>675</y244>
			<x245>603</x245>
			<y245>676</y245>
			<x246>604</x246>
			<y246>676</y246>
			<x247>605</x247>
			<y247>677</y247>
			<x248>606</x248>
			<y248>677</y248>
			<x249>607</x249>
			<y249>678</y249>
			<x250>608</x250>
			<y250>678</y250>
			<x251>609</x251>
			<y251>679</y251>
			<x252>610</x252>
			<y252>679</y252>
			<x253>612</x253>
			<y253>681</y253>
			<x254>613</x254>
			<y254>681</y254>
			<x255>614</x255>
			<y255>682</y255>
			<x256>615</x256>
			<y256>682</y256>
			<x257>616</x257>
			<y257>683</y257>
			<x258>617</x258>
			<y258>683</y258>
			<x259>619</x259>
			<y259>685</y259>
			<x260>619</x260>
			<y260>686</y260>
			<x261>620</x261>
			<y261>687</y261>
			<x262>620</x262>
			<y262>688</y262>
			<x263>621</x263>
			<y263>689</y263>
			<x264>621</x264>
			<y264>690</y264>
			<x265>622</x265>
			<y265>691</y265>
			<x266>622</x266>
			<y266>692</y266>
			<x267>623</x267>
			<y267>693</y267>
			<x268>623</x268>
			<y268>694</y268>
			<x269>625</x269>
			<y269>696</y269>
			<x270>625</x270>
			<y270>697</y270>
			<x271>628</x271>
			<y271>700</y271>
			<x272>628</x272>
			<y272>701</y272>
			<x273>630</x273>
			<y273>703</y273>
			<x274>631</x274>
			<y274>703</y274>
			<x275>632</x275>
			<y275>704</y275>
			<x276>633</x276>
			<y276>704</y276>
			<x277>634</x277>
			<y277>705</y277>
			<x278>635</x278>
			<y278>705</y278>
			<x279>636</x279>
			<y279>706</y279>
			<x280>637</x280>
			<y280>706</y280>
			<x281>638</x281>
			<y281>707</y281>
			<x282>640</x282>
			<y282>707</y282>
			<x283>641</x283>
			<y283>708</y283>
			<x284>645</x284>
			<y284>708</y284>
			<x285>646</x285>
			<y285>709</y285>
			<x286>650</x286>
			<y286>709</y286>
			<x287>651</x287>
			<y287>710</y287>
			<x288>665</x288>
			<y288>710</y288>
			<x289>666</x289>
			<y289>709</y289>
			<x290>672</x290>
			<y290>709</y290>
			<x291>673</x291>
			<y291>708</y291>
			<x292>679</x292>
			<y292>708</y292>
			<x293>680</x293>
			<y293>707</y293>
			<x294>683</x294>
			<y294>707</y294>
			<x295>684</x295>
			<y295>706</y295>
			<x296>685</x296>
			<y296>706</y296>
			<x297>686</x297>
			<y297>705</y297>
			<x298>687</x298>
			<y298>705</y298>
			<x299>688</x299>
			<y299>704</y299>
			<x300>688</x300>
			<y300>703</y300>
			<x301>689</x301>
			<y301>702</y301>
			<x302>689</x302>
			<y302>701</y302>
			<x303>690</x303>
			<y303>700</y303>
			<x304>690</x304>
			<y304>699</y304>
			<x305>691</x305>
			<y305>698</y305>
			<x306>691</x306>
			<y306>697</y306>
			<x307>693</x307>
			<y307>695</y307>
			<x308>693</x308>
			<y308>694</y308>
			<x309>694</x309>
			<y309>693</y309>
			<x310>694</x310>
			<y310>692</y310>
			<x311>698</x311>
			<y311>688</y311>
			<x312>698</x312>
			<y312>687</y312>
			<x313>700</x313>
			<y313>685</y313>
			<x314>701</x314>
			<y314>685</y314>
			<x315>702</x315>
			<y315>684</y315>
			<x316>704</x316>
			<y316>684</y316>
			<x317>705</x317>
			<y317>683</y317>
			<x318>708</x318>
			<y318>683</y318>
			<x319>709</x319>
			<y319>682</y319>
			<x320>711</x320>
			<y320>682</y320>
			<x321>712</x321>
			<y321>681</y321>
			<x322>715</x322>
			<y322>681</y322>
			<x323>716</x323>
			<y323>680</y323>
			<x324>718</x324>
			<y324>680</y324>
			<x325>719</x325>
			<y325>679</y325>
			<x326>721</x326>
			<y326>679</y326>
			<x327>722</x327>
			<y327>678</y327>
			<x328>723</x328>
			<y328>678</y328>
			<x329>724</x329>
			<y329>677</y329>
			<x330>726</x330>
			<y330>677</y330>
			<x331>727</x331>
			<y331>676</y331>
			<x332>729</x332>
			<y332>676</y332>
			<x333>730</x333>
			<y333>675</y333>
			<x334>732</x334>
			<y334>675</y334>
			<x335>733</x335>
			<y335>674</y335>
			<x336>734</x336>
			<y336>674</y336>
			<x337>735</x337>
			<y337>673</y337>
			<x338>736</x338>
			<y338>673</y338>
			<x339>737</x339>
			<y339>672</y339>
			<x340>738</x340>
			<y340>672</y340>
			<x341>739</x341>
			<y341>671</y341>
			<x342>740</x342>
			<y342>671</y342>
			<x343>741</x343>
			<y343>670</y343>
			<x344>742</x344>
			<y344>670</y344>
			<x345>743</x345>
			<y345>669</y345>
			<x346>744</x346>
			<y346>669</y346>
			<x347>745</x347>
			<y347>668</y347>
			<x348>746</x348>
			<y348>668</y348>
			<x349>747</x349>
			<y349>667</y349>
			<x350>748</x350>
			<y350>667</y350>
			<x351>749</x351>
			<y351>666</y351>
			<x352>750</x352>
			<y352>666</y352>
			<x353>751</x353>
			<y353>665</y353>
			<x354>752</x354>
			<y354>665</y354>
			<x355>753</x355>
			<y355>664</y355>
			<x356>754</x356>
			<y356>664</y356>
			<x357>756</x357>
			<y357>662</y357>
			<x358>757</x358>
			<y358>662</y358>
			<x359>758</x359>
			<y359>661</y359>
			<x360>759</x360>
			<y360>661</y360>
			<x361>760</x361>
			<y361>660</y361>
			<x362>761</x362>
			<y362>660</y362>
			<x363>763</x363>
			<y363>658</y363>
			<x364>764</x364>
			<y364>658</y364>
			<x365>765</x365>
			<y365>657</y365>
			<x366>766</x366>
			<y366>657</y366>
			<x367>767</x367>
			<y367>656</y367>
			<x368>768</x368>
			<y368>656</y368>
			<x369>771</x369>
			<y369>653</y369>
			<x370>772</x370>
			<y370>653</y370>
			<x371>777</x371>
			<y371>648</y371>
			<x372>778</x372>
			<y372>648</y372>
			<x373>782</x373>
			<y373>644</y373>
			<x374>782</x374>
			<y374>643</y374>
			<x375>784</x375>
			<y375>641</y375>
			<x376>784</x376>
			<y376>640</y376>
			<x377>786</x377>
			<y377>638</y377>
			<x378>786</x378>
			<y378>637</y378>
			<x379>788</x379>
			<y379>635</y379>
			<x380>788</x380>
			<y380>634</y380>
			<x381>789</x381>
			<y381>633</y381>
			<x382>789</x382>
			<y382>632</y382>
			<x383>791</x383>
			<y383>630</y383>
			<x384>791</x384>
			<y384>629</y384>
			<x385>792</x385>
			<y385>628</y385>
			<x386>792</x386>
			<y386>627</y386>
			<x387>793</x387>
			<y387>626</y387>
			<x388>793</x388>
			<y388>625</y388>
			<x389>795</x389>
			<y389>623</y389>
			<x390>795</x390>
			<y390>622</y390>
			<x391>798</x391>
			<y391>619</y391>
			<x392>798</x392>
			<y392>618</y392>
			<x393>799</x393>
			<y393>617</y393>
			<x394>799</x394>
			<y394>616</y394>
			<x395>800</x395>
			<y395>615</y395>
			<x396>800</x396>
			<y396>612</y396>
			<x397>801</x397>
			<y397>611</y397>
			<x398>801</x398>
			<y398>607</y398>
			<x399>802</x399>
			<y399>606</y399>
			<x400>802</x400>
			<y400>594</y400>
			<x401>803</x401>
			<y401>593</y401>
			<x402>803</x402>
			<y402>592</y402>
			<x403>804</x403>
			<y403>591</y403>
			<x404>804</x404>
			<y404>590</y404>
			<x405>805</x405>
			<y405>589</y405>
			<x406>805</x406>
			<y406>588</y406>
			<x407>806</x407>
			<y407>587</y407>
			<x408>806</x408>
			<y408>586</y408>
			<x409>807</x409>
			<y409>585</y409>
			<x410>807</x410>
			<y410>584</y410>
			<x411>808</x411>
			<y411>583</y411>
			<x412>808</x412>
			<y412>582</y412>
			<x413>809</x413>
			<y413>581</y413>
			<x414>809</x414>
			<y414>558</y414>
			<x415>808</x415>
			<y415>557</y415>
			<x416>808</x416>
			<y416>553</y416>
			<x417>807</x417>
			<y417>552</y417>
			<x418>807</x418>
			<y418>549</y418>
			<x419>806</x419>
			<y419>548</y419>
			<x420>806</x420>
			<y420>545</y420>
			<x421>805</x421>
			<y421>544</y421>
			<x422>805</x422>
			<y422>540</y422>
			<x423>804</x423>
			<y423>539</y423>
			<x424>804</x424>
			<y424>536</y424>
			<x425>803</x425>
			<y425>535</y425>
			<x426>803</x426>
			<y426>532</y426>
			<x427>802</x427>
			<y427>531</y427>
			<x428>802</x428>
			<y428>529</y428>
			<x429>801</x429>
			<y429>528</y429>
			<x430>801</x430>
			<y430>527</y430>
			<x431>800</x431>
			<y431>526</y431>
			<x432>800</x432>
			<y432>525</y432>
			<x433>799</x433>
			<y433>524</y433>
			<x434>799</x434>
			<y434>523</y434>
			<x435>798</x435>
			<y435>522</y435>
			<x436>798</x436>
			<y436>521</y436>
			<x437>796</x437>
			<y437>519</y437>
			<x438>796</x438>
			<y438>518</y438>
			<x439>795</x439>
			<y439>517</y439>
			<x440>795</x440>
			<y440>516</y440>
			<x441>794</x441>
			<y441>515</y441>
			<x442>794</x442>
			<y442>514</y442>
			<x443>793</x443>
			<y443>513</y443>
			<x444>793</x444>
			<y444>512</y444>
			<x445>792</x445>
			<y445>511</y445>
			<x446>792</x446>
			<y446>510</y446>
			<x447>788</x447>
			<y447>506</y447>
			<x448>788</x448>
			<y448>505</y448>
			<x449>781</x449>
			<y449>498</y449>
			<x450>781</x450>
			<y450>497</y450>
			<x451>773</x451>
			<y451>489</y451>
			<x452>773</x452>
			<y452>488</y452>
			<x453>768</x453>
			<y453>483</y453>
			<x454>767</x454>
			<y454>483</y454>
			<x455>766</x455>
			<y455>482</y455>
			<x456>765</x456>
			<y456>482</y456>
			<x457>764</x457>
			<y457>481</y457>
			<x458>763</x458>
			<y458>481</y458>
			<x459>761</x459>
			<y459>479</y459>
			<x460>760</x460>
			<y460>479</y460>
			<x461>759</x461>
			<y461>478</y461>
			<x462>758</x462>
			<y462>478</y462>
			<x463>757</x463>
			<y463>477</y463>
			<x464>756</x464>
			<y464>477</y464>
			<x465>755</x465>
			<y465>476</y465>
			<x466>752</x466>
			<y466>476</y466>
			<x467>751</x467>
			<y467>475</y467>
			<x468>749</x468>
			<y468>475</y468>
			<x469>748</x469>
			<y469>474</y469>
			<x470>747</x470>
			<y470>474</y470>
			<x471>746</x471>
			<y471>473</y471>
			<x472>746</x472>
			<y472>472</y472>
			<x473>745</x473>
			<y473>471</y473>
			<x474>745</x474>
			<y474>470</y474>
			<x475>744</x475>
			<y475>469</y475>
			<x476>744</x476>
			<y476>468</y476>
			<x477>743</x477>
			<y477>467</y477>
			<x478>743</x478>
			<y478>466</y478>
			<x479>742</x479>
			<y479>465</y479>
			<x480>741</x480>
			<y480>465</y480>
			<x481>740</x481>
			<y481>464</y481>
			<x482>739</x482>
			<y482>464</y482>
			<x483>737</x483>
			<y483>462</y483>
			<x484>736</x484>
			<y484>462</y484>
			<x485>734</x485>
			<y485>460</y485>
			<x486>733</x486>
			<y486>460</y486>
			<x487>732</x487>
			<y487>459</y487>
			<x488>731</x488>
			<y488>459</y488>
			<x489>727</x489>
			<y489>455</y489>
			<x490>726</x490>
			<y490>455</y490>
			<x491>722</x491>
			<y491>451</y491>
			<x492>721</x492>
			<y492>451</y492>
			<x493>719</x493>
			<y493>449</y493>
			<x494>718</x494>
			<y494>449</y494>
			<x495>717</x495>
			<y495>448</y495>
			<x496>714</x496>
			<y496>448</y496>
			<x497>713</x497>
			<y497>447</y497>
			<x498>711</x498>
			<y498>447</y498>
			<x499>709</x499>
			<y499>445</y499>
			<x500>709</x500>
			<y500>438</y500>
			<x501>708</x501>
			<y501>437</y501>
			<x502>708</x502>
			<y502>415</y502>
			<x503>707</x503>
			<y503>414</y503>
			<x504>706</x504>
			<y504>414</y504>
			<x505>704</x505>
			<y505>412</y505>
			<x506>703</x506>
			<y506>412</y506>
			<x507>701</x507>
			<y507>410</y507>
			<x508>700</x508>
			<y508>410</y508>
			<x509>698</x509>
			<y509>408</y509>
			<x510>697</x510>
			<y510>408</y510>
			<x511>696</x511>
			<y511>407</y511>
			<x512>695</x512>
			<y512>407</y512>
			<x513>694</x513>
			<y513>406</y513>
			<x514>691</x514>
			<y514>406</y514>
			<x515>690</x515>
			<y515>405</y515>
			<x516>687</x516>
			<y516>405</y516>
			<x517>686</x517>
			<y517>406</y517>
			<x518>682</x518>
			<y518>406</y518>
		</polygon>
	</object>
	<object>
		<name>bloodstain</name>
		<pose>Unspecified</pose>
		<truncated>0</truncated>
		<difficult>0</difficult>
		<occluded>0</occluded>
		<bndbox>
			<xmin>258</xmin>
			<xmax>373</xmax>
			<ymin>441</ymin>
			<ymax>483</ymax>
		</bndbox>
		<polygon>
			<x1>258</x1>
			<y1>445</y1>
			<x2>257</x2>
			<y2>446</y2>
			<x3>257</x3>
			<y3>453</y3>
			<x4>258</x4>
			<y4>454</y4>
			<x5>257</x5>
			<y5>455</y5>
			<x6>257</x6>
			<y6>464</y6>
			<x7>258</x7>
			<y7>465</y7>
			<x8>258</x8>
			<y8>467</y8>
			<x9>260</x9>
			<y9>469</y9>
			<x10>260</x10>
			<y10>470</y10>
			<x11>263</x11>
			<y11>473</y11>
			<x12>263</x12>
			<y12>474</y12>
			<x13>270</x13>
			<y13>481</y13>
			<x14>301</x14>
			<y14>481</y14>
			<x15>302</x15>
			<y15>482</y15>
			<x16>309</x16>
			<y16>482</y16>
			<x17>310</x17>
			<y17>481</y17>
			<x18>320</x18>
			<y18>481</y18>
			<x19>321</x19>
			<y19>482</y19>
			<x20>330</x20>
			<y20>482</y20>
			<x21>331</x21>
			<y21>481</y21>
			<x22>355</x22>
			<y22>481</y22>
			<x23>356</x23>
			<y23>480</y23>
			<x24>366</x24>
			<y24>480</y24>
			<x25>367</x25>
			<y25>481</y25>
			<x26>371</x26>
			<y26>481</y26>
			<x27>371</x27>
			<y27>470</y27>
			<x28>372</x28>
			<y28>469</y28>
			<x29>372</x29>
			<y29>458</y29>
			<x30>371</x30>
			<y30>457</y30>
			<x31>371</x31>
			<y31>455</y31>
			<x32>370</x32>
			<y32>454</y32>
			<x33>370</x33>
			<y33>453</y33>
			<x34>369</x34>
			<y34>452</y34>
			<x35>369</x35>
			<y35>451</y35>
			<x36>368</x36>
			<y36>450</y36>
			<x37>368</x37>
			<y37>449</y37>
			<x38>367</x38>
			<y38>448</y38>
			<x39>366</x39>
			<y39>448</y39>
			<x40>365</x40>
			<y40>447</y40>
			<x41>363</x41>
			<y41>447</y41>
			<x42>362</x42>
			<y42>448</y42>
			<x43>360</x43>
			<y43>448</y43>
			<x44>359</x44>
			<y44>449</y44>
			<x45>358</x45>
			<y45>449</y45>
			<x46>357</x46>
			<y46>450</y46>
			<x47>357</x47>
			<y47>451</y47>
			<x48>356</x48>
			<y48>452</y48>
			<x49>356</x49>
			<y49>454</y49>
			<x50>355</x50>
			<y50>455</y50>
			<x51>355</x51>
			<y51>460</y51>
			<x52>356</x52>
			<y52>461</y52>
			<x53>355</x53>
			<y53>462</y53>
			<x54>355</x54>
			<y54>463</y54>
			<x55>356</x55>
			<y55>464</y55>
			<x56>356</x56>
			<y56>468</y56>
			<x57>357</x57>
			<y57>469</y57>
			<x58>357</x58>
			<y58>470</y58>
			<x59>358</x59>
			<y59>471</y59>
			<x60>358</x60>
			<y60>473</y60>
			<x61>357</x61>
			<y61>474</y61>
			<x62>356</x62>
			<y62>474</y62>
			<x63>355</x63>
			<y63>473</y63>
			<x64>354</x64>
			<y64>473</y64>
			<x65>351</x65>
			<y65>470</y65>
			<x66>350</x66>
			<y66>470</y66>
			<x67>348</x67>
			<y67>468</y67>
			<x68>347</x68>
			<y68>468</y68>
			<x69>346</x69>
			<y69>467</y69>
			<x70>345</x70>
			<y70>467</y70>
			<x71>344</x71>
			<y71>466</y71>
			<x72>343</x72>
			<y72>466</y72>
			<x73>342</x73>
			<y73>465</y73>
			<x74>340</x74>
			<y74>465</y74>
			<x75>339</x75>
			<y75>464</y75>
			<x76>338</x76>
			<y76>464</y76>
			<x77>336</x77>
			<y77>462</y77>
			<x78>335</x78>
			<y78>462</y78>
			<x79>334</x79>
			<y79>461</y79>
			<x80>333</x80>
			<y80>461</y80>
			<x81>332</x81>
			<y81>462</y81>
			<x82>330</x82>
			<y82>462</y82>
			<x83>329</x83>
			<y83>463</y83>
			<x84>325</x84>
			<y84>463</y84>
			<x85>324</x85>
			<y85>462</y85>
			<x86>314</x86>
			<y86>462</y86>
			<x87>313</x87>
			<y87>463</y87>
			<x88>312</x88>
			<y88>463</y88>
			<x89>311</x89>
			<y89>464</y89>
			<x90>305</x90>
			<y90>464</y90>
			<x91>304</x91>
			<y91>463</y91>
			<x92>301</x92>
			<y92>463</y92>
			<x93>300</x93>
			<y93>462</y93>
			<x94>298</x94>
			<y94>462</y94>
			<x95>297</x95>
			<y95>461</y95>
			<x96>297</x96>
			<y96>460</y96>
			<x97>295</x97>
			<y97>458</y97>
			<x98>295</x98>
			<y98>457</y98>
			<x99>293</x99>
			<y99>455</y99>
			<x100>293</x100>
			<y100>454</y100>
			<x101>290</x101>
			<y101>451</y101>
			<x102>290</x102>
			<y102>450</y102>
			<x103>287</x103>
			<y103>447</y103>
			<x104>286</x104>
			<y104>447</y104>
			<x105>285</x105>
			<y105>446</y105>
			<x106>284</x106>
			<y106>446</y106>
			<x107>282</x107>
			<y107>444</y107>
			<x108>282</x108>
			<y108>443</y108>
			<x109>281</x109>
			<y109>442</y109>
			<x110>280</x110>
			<y110>442</y110>
			<x111>279</x111>
			<y111>441</y111>
			<x112>278</x112>
			<y112>441</y112>
			<x113>277</x113>
			<y113>440</y113>
			<x114>273</x114>
			<y114>440</y114>
			<x115>272</x115>
			<y115>441</y115>
			<x116>269</x116>
			<y116>441</y116>
			<x117>268</x117>
			<y117>442</y117>
			<x118>266</x118>
			<y118>442</y118>
			<x119>265</x119>
			<y119>441</y119>
			<x120>264</x120>
			<y120>441</y120>
			<x121>263</x121>
			<y121>440</y121>
			<x122>261</x122>
			<y122>440</y122>
			<x123>258</x123>
			<y123>443</y123>
			<x124>258</x124>
			<y124>445</y124>
		</polygon>
	</object>
	<object>
		<name>bloodstain</name>
		<pose>Unspecified</pose>
		<truncated>0</truncated>
		<difficult>0</difficult>
		<occluded>0</occluded>
		<bndbox>
			<xmin>293</xmin>
			<xmax>373</xmax>
			<ymin>485</ymin>
			<ymax>497</ymax>
		</bndbox>
		<polygon>
			<x1>295</x1>
			<y1>485</y1>
			<x2>294</x2>
			<y2>486</y2>
			<x3>293</x3>
			<y3>486</y3>
			<x4>293</x4>
			<y4>487</y4>
			<x5>292</x5>
			<y5>488</y5>
			<x6>293</x6>
			<y6>489</y6>
			<x7>302</x7>
			<y7>489</y7>
			<x8>303</x8>
			<y8>490</y8>
			<x9>306</x9>
			<y9>490</y9>
			<x10>307</x10>
			<y10>491</y10>
			<x11>308</x11>
			<y11>491</y11>
			<x12>309</x12>
			<y12>492</y12>
			<x13>312</x13>
			<y13>492</y13>
			<x14>313</x14>
			<y14>493</y14>
			<x15>316</x15>
			<y15>493</y15>
			<x16>317</x16>
			<y16>492</y16>
			<x17>319</x17>
			<y17>492</y17>
			<x18>320</x18>
			<y18>491</y18>
			<x19>324</x19>
			<y19>491</y19>
			<x20>325</x20>
			<y20>490</y20>
			<x21>326</x21>
			<y21>490</y21>
			<x22>327</x22>
			<y22>489</y22>
			<x23>340</x23>
			<y23>489</y23>
			<x24>341</x24>
			<y24>490</y24>
			<x25>342</x25>
			<y25>490</y25>
			<x26>344</x26>
			<y26>492</y26>
			<x27>345</x27>
			<y27>492</y27>
			<x28>347</x28>
			<y28>494</y28>
			<x29>348</x29>
			<y29>494</y29>
			<x30>349</x30>
			<y30>495</y30>
			<x31>351</x31>
			<y31>495</y31>
			<x32>352</x32>
			<y32>494</y32>
			<x33>354</x33>
			<y33>494</y33>
			<x34>356</x34>
			<y34>496</y34>
			<x35>357</x35>
			<y35>496</y35>
			<x36>358</x36>
			<y36>495</y36>
			<x37>359</x37>
			<y37>495</y37>
			<x38>359</x38>
			<y38>494</y38>
			<x39>360</x39>
			<y39>493</y39>
			<x40>363</x40>
			<y40>493</y40>
			<x41>364</x41>
			<y41>492</y41>
			<x42>365</x42>
			<y42>492</y42>
			<x43>366</x43>
			<y43>491</y43>
			<x44>368</x44>
			<y44>491</y44>
			<x45>369</x45>
			<y45>490</y45>
			<x46>370</x46>
			<y46>490</y46>
			<x47>371</x47>
			<y47>489</y47>
			<x48>372</x48>
			<y48>489</y48>
			<x49>372</x49>
			<y49>485</y49>
			<x50>362</x50>
			<y50>485</y50>
			<x51>361</x51>
			<y51>484</y51>
			<x52>330</x52>
			<y52>484</y52>
			<x53>329</x53>
			<y53>485</y53>
			<x54>319</x54>
			<y54>485</y54>
			<x55>318</x55>
			<y55>484</y55>
			<x56>297</x56>
			<y56>484</y56>
			<x57>296</x57>
			<y57>485</y57>
			<x58>295</x58>
			<y58>485</y58>
		</polygon>
	</object>
</annotation>
