<annotation>
	<folder></folder>
	<filename>1_w_blood-marks_21_jpg.rf.8b3d93f86ee9baefd24e3ebcf7b1eeeb.jpg</filename>
	<path>1_w_blood-marks_21_jpg.rf.8b3d93f86ee9baefd24e3ebcf7b1eeeb.jpg</path>
	<source>
		<database>roboflow.com</database>
	</source>
	<size>
		<width>1086</width>
		<height>860</height>
		<depth>3</depth>
	</size>
	<segmented>0</segmented>
	<object>
		<name>bloodstain</name>
		<pose>Unspecified</pose>
		<truncated>0</truncated>
		<difficult>0</difficult>
		<occluded>0</occluded>
		<bndbox>
			<xmin>713</xmin>
			<xmax>814</xmax>
			<ymin>337</ymin>
			<ymax>439</ymax>
		</bndbox>
		<polygon>
			<x1>761</x1>
			<y1>338</y1>
			<x2>756</x2>
			<y2>338</y2>
			<x3>755</x3>
			<y3>337</y3>
			<x4>753</x4>
			<y4>337</y4>
			<x5>753</x5>
			<y5>338</y5>
			<x6>752</x6>
			<y6>339</y6>
			<x7>752</x7>
			<y7>340</y7>
			<x8>751</x8>
			<y8>341</y8>
			<x9>747</x9>
			<y9>341</y9>
			<x10>746</x10>
			<y10>340</y10>
			<x11>746</x11>
			<y11>339</y11>
			<x12>745</x12>
			<y12>338</y12>
			<x13>744</x13>
			<y13>338</y13>
			<x14>743</x14>
			<y14>339</y14>
			<x15>743</x15>
			<y15>342</y15>
			<x16>744</x16>
			<y16>343</y16>
			<x17>742</x17>
			<y17>345</y17>
			<x18>738</x18>
			<y18>345</y18>
			<x19>737</x19>
			<y19>344</y19>
			<x20>734</x20>
			<y20>344</y20>
			<x21>734</x21>
			<y21>345</y21>
			<x22>733</x22>
			<y22>346</y22>
			<x23>733</x23>
			<y23>348</y23>
			<x24>732</x24>
			<y24>349</y24>
			<x25>732</x25>
			<y25>350</y25>
			<x26>730</x26>
			<y26>352</y26>
			<x27>725</x27>
			<y27>352</y27>
			<x28>725</x28>
			<y28>353</y28>
			<x29>724</x29>
			<y29>354</y29>
			<x30>724</x30>
			<y30>355</y30>
			<x31>723</x31>
			<y31>356</y31>
			<x32>723</x32>
			<y32>357</y32>
			<x33>721</x33>
			<y33>359</y33>
			<x34>721</x34>
			<y34>361</y34>
			<x35>720</x35>
			<y35>362</y35>
			<x36>721</x36>
			<y36>363</y36>
			<x37>721</x37>
			<y37>368</y37>
			<x38>720</x38>
			<y38>369</y38>
			<x39>720</x39>
			<y39>370</y39>
			<x40>716</x40>
			<y40>374</y40>
			<x41>715</x41>
			<y41>374</y41>
			<x42>715</x42>
			<y42>375</y42>
			<x43>714</x43>
			<y43>376</y43>
			<x44>715</x44>
			<y44>377</y44>
			<x45>715</x45>
			<y45>379</y45>
			<x46>717</x46>
			<y46>381</y46>
			<x47>715</x47>
			<y47>383</y47>
			<x48>712</x48>
			<y48>383</y48>
			<x49>712</x49>
			<y49>385</y49>
			<x50>715</x50>
			<y50>388</y50>
			<x51>715</x51>
			<y51>390</y51>
			<x52>716</x52>
			<y52>391</y52>
			<x53>716</x53>
			<y53>397</y53>
			<x54>714</x54>
			<y54>399</y54>
			<x55>714</x55>
			<y55>402</y55>
			<x56>716</x56>
			<y56>404</y56>
			<x57>716</x57>
			<y57>405</y57>
			<x58>717</x58>
			<y58>406</y58>
			<x59>717</x59>
			<y59>407</y59>
			<x60>718</x60>
			<y60>408</y60>
			<x61>718</x61>
			<y61>409</y61>
			<x62>719</x62>
			<y62>410</y62>
			<x63>719</x63>
			<y63>411</y63>
			<x64>720</x64>
			<y64>412</y64>
			<x65>720</x65>
			<y65>413</y65>
			<x66>721</x66>
			<y66>414</y66>
			<x67>721</x67>
			<y67>417</y67>
			<x68>723</x68>
			<y68>419</y68>
			<x69>724</x69>
			<y69>419</y69>
			<x70>726</x70>
			<y70>421</y70>
			<x71>727</x71>
			<y71>421</y71>
			<x72>730</x72>
			<y72>424</y72>
			<x73>730</x73>
			<y73>426</y73>
			<x74>731</x74>
			<y74>427</y74>
			<x75>734</x75>
			<y75>427</y75>
			<x76>738</x76>
			<y76>431</y76>
			<x77>738</x77>
			<y77>432</y77>
			<x78>740</x78>
			<y78>434</y78>
			<x79>744</x79>
			<y79>434</y79>
			<x80>745</x80>
			<y80>435</y80>
			<x81>746</x81>
			<y81>435</y81>
			<x82>747</x82>
			<y82>434</y82>
			<x83>749</x83>
			<y83>434</y83>
			<x84>750</x84>
			<y84>435</y84>
			<x85>750</x85>
			<y85>436</y85>
			<x86>752</x86>
			<y86>438</y86>
			<x87>753</x87>
			<y87>437</y87>
			<x88>753</x88>
			<y88>436</y88>
			<x89>754</x89>
			<y89>435</y89>
			<x90>755</x90>
			<y90>435</y90>
			<x91>756</x91>
			<y91>434</y91>
			<x92>761</x92>
			<y92>434</y92>
			<x93>762</x93>
			<y93>435</y93>
			<x94>763</x94>
			<y94>435</y94>
			<x95>764</x95>
			<y95>436</y95>
			<x96>765</x96>
			<y96>436</y96>
			<x97>766</x97>
			<y97>437</y97>
			<x98>767</x98>
			<y98>437</y98>
			<x99>768</x99>
			<y99>438</y99>
			<x100>769</x100>
			<y100>437</y100>
			<x101>769</x101>
			<y101>436</y101>
			<x102>772</x102>
			<y102>433</y102>
			<x103>776</x103>
			<y103>433</y103>
			<x104>777</x104>
			<y104>434</y104>
			<x105>778</x105>
			<y105>434</y105>
			<x106>779</x106>
			<y106>435</y106>
			<x107>780</x107>
			<y107>435</y107>
			<x108>781</x108>
			<y108>434</y108>
			<x109>781</x109>
			<y109>433</y109>
			<x110>782</x110>
			<y110>432</y110>
			<x111>782</x111>
			<y111>431</y111>
			<x112>783</x112>
			<y112>430</y112>
			<x113>784</x113>
			<y113>430</y113>
			<x114>785</x114>
			<y114>429</y114>
			<x115>786</x115>
			<y115>429</y115>
			<x116>787</x116>
			<y116>428</y116>
			<x117>789</x117>
			<y117>428</y117>
			<x118>791</x118>
			<y118>426</y118>
			<x119>798</x119>
			<y119>426</y119>
			<x120>798</x120>
			<y120>423</y120>
			<x121>797</x121>
			<y121>422</y121>
			<x122>797</x122>
			<y122>418</y122>
			<x123>798</x123>
			<y123>417</y123>
			<x124>800</x124>
			<y124>417</y124>
			<x125>801</x125>
			<y125>416</y125>
			<x126>801</x126>
			<y126>415</y126>
			<x127>804</x127>
			<y127>412</y127>
			<x128>808</x128>
			<y128>412</y128>
			<x129>808</x129>
			<y129>409</y129>
			<x130>807</x130>
			<y130>408</y130>
			<x131>807</x131>
			<y131>407</y131>
			<x132>806</x132>
			<y132>406</y132>
			<x133>806</x133>
			<y133>404</y133>
			<x134>807</x134>
			<y134>403</y134>
			<x135>808</x135>
			<y135>403</y135>
			<x136>809</x136>
			<y136>402</y136>
			<x137>810</x137>
			<y137>402</y137>
			<x138>811</x138>
			<y138>401</y138>
			<x139>812</x139>
			<y139>401</y139>
			<x140>811</x140>
			<y140>400</y140>
			<x141>811</x141>
			<y141>398</y141>
			<x142>810</x142>
			<y142>397</y142>
			<x143>810</x143>
			<y143>385</y143>
			<x144>811</x144>
			<y144>384</y144>
			<x145>811</x145>
			<y145>381</y145>
			<x146>812</x146>
			<y146>380</y146>
			<x147>812</x147>
			<y147>377</y147>
			<x148>813</x148>
			<y148>376</y148>
			<x149>813</x149>
			<y149>375</y149>
			<x150>812</x150>
			<y150>375</y150>
			<x151>810</x151>
			<y151>373</y151>
			<x152>810</x152>
			<y152>371</y152>
			<x153>809</x153>
			<y153>370</y153>
			<x154>809</x154>
			<y154>368</y154>
			<x155>808</x155>
			<y155>367</y155>
			<x156>808</x156>
			<y156>366</y156>
			<x157>807</x157>
			<y157>365</y157>
			<x158>807</x158>
			<y158>363</y158>
			<x159>806</x159>
			<y159>362</y159>
			<x160>806</x160>
			<y160>360</y160>
			<x161>805</x161>
			<y161>359</y161>
			<x162>805</x162>
			<y162>358</y162>
			<x163>804</x163>
			<y163>357</y163>
			<x164>799</x164>
			<y164>357</y164>
			<x165>796</x165>
			<y165>354</y165>
			<x166>796</x166>
			<y166>353</y166>
			<x167>794</x167>
			<y167>351</y167>
			<x168>794</x168>
			<y168>349</y168>
			<x169>795</x169>
			<y169>348</y169>
			<x170>795</x170>
			<y170>346</y170>
			<x171>790</x171>
			<y171>346</y171>
			<x172>787</x172>
			<y172>343</y172>
			<x173>787</x173>
			<y173>342</y173>
			<x174>786</x174>
			<y174>341</y174>
			<x175>786</x175>
			<y175>340</y175>
			<x176>785</x176>
			<y176>340</y176>
			<x177>784</x177>
			<y177>339</y177>
			<x178>782</x178>
			<y178>341</y178>
			<x179>781</x179>
			<y179>341</y179>
			<x180>780</x180>
			<y180>342</y180>
			<x181>778</x181>
			<y181>342</y181>
			<x182>777</x182>
			<y182>341</y182>
			<x183>776</x183>
			<y183>341</y183>
			<x184>775</x184>
			<y184>340</y184>
			<x185>774</x185>
			<y185>340</y185>
			<x186>773</x186>
			<y186>339</y186>
			<x187>768</x187>
			<y187>339</y187>
			<x188>767</x188>
			<y188>340</y188>
			<x189>766</x189>
			<y189>340</y189>
			<x190>765</x190>
			<y190>339</y190>
			<x191>765</x191>
			<y191>338</y191>
			<x192>764</x192>
			<y192>337</y192>
			<x193>764</x193>
			<y193>336</y193>
			<x194>762</x194>
			<y194>336</y194>
			<x195>762</x195>
			<y195>337</y195>
			<x196>761</x196>
			<y196>338</y196>
		</polygon>
	</object>
	<object>
		<name>bloodstain</name>
		<pose>Unspecified</pose>
		<truncated>0</truncated>
		<difficult>0</difficult>
		<occluded>0</occluded>
		<bndbox>
			<xmin>692</xmin>
			<xmax>740</xmax>
			<ymin>273</ymin>
			<ymax>323</ymax>
		</bndbox>
		<polygon>
			<x1>709</x1>
			<y1>275</y1>
			<x2>708</x2>
			<y2>274</y2>
			<x3>708</x3>
			<y3>273</y3>
			<x4>706</x4>
			<y4>273</y4>
			<x5>706</x5>
			<y5>274</y5>
			<x6>705</x6>
			<y6>275</y6>
			<x7>705</x7>
			<y7>276</y7>
			<x8>704</x8>
			<y8>277</y8>
			<x9>703</x9>
			<y9>277</y9>
			<x10>698</x10>
			<y10>282</y10>
			<x11>697</x11>
			<y11>282</y11>
			<x12>696</x12>
			<y12>283</y12>
			<x13>695</x13>
			<y13>283</y13>
			<x14>694</x14>
			<y14>284</y14>
			<x15>694</x15>
			<y15>285</y15>
			<x16>693</x16>
			<y16>286</y16>
			<x17>694</x17>
			<y17>287</y17>
			<x18>693</x18>
			<y18>288</y18>
			<x19>693</x19>
			<y19>297</y19>
			<x20>692</x20>
			<y20>298</y20>
			<x21>692</x21>
			<y21>301</y21>
			<x22>691</x22>
			<y22>302</y22>
			<x23>692</x23>
			<y23>303</y23>
			<x24>692</x24>
			<y24>305</y24>
			<x25>695</x25>
			<y25>308</y25>
			<x26>695</x26>
			<y26>309</y26>
			<x27>696</x27>
			<y27>310</y27>
			<x28>698</x28>
			<y28>310</y28>
			<x29>699</x29>
			<y29>311</y29>
			<x30>699</x30>
			<y30>312</y30>
			<x31>702</x31>
			<y31>315</y31>
			<x32>702</x32>
			<y32>316</y32>
			<x33>704</x33>
			<y33>318</y33>
			<x34>705</x34>
			<y34>317</y34>
			<x35>707</x35>
			<y35>317</y35>
			<x36>708</x36>
			<y36>318</y36>
			<x37>709</x37>
			<y37>318</y37>
			<x38>713</x38>
			<y38>322</y38>
			<x39>719</x39>
			<y39>322</y39>
			<x40>720</x40>
			<y40>321</y40>
			<x41>721</x41>
			<y41>321</y41>
			<x42>722</x42>
			<y42>320</y42>
			<x43>728</x43>
			<y43>320</y43>
			<x44>728</x44>
			<y44>316</y44>
			<x45>729</x45>
			<y45>315</y45>
			<x46>733</x46>
			<y46>315</y46>
			<x47>733</x47>
			<y47>310</y47>
			<x48>735</x48>
			<y48>308</y48>
			<x49>738</x49>
			<y49>308</y49>
			<x50>738</x50>
			<y50>304</y50>
			<x51>736</x51>
			<y51>302</y51>
			<x52>736</x52>
			<y52>301</y52>
			<x53>738</x53>
			<y53>299</y53>
			<x54>739</x54>
			<y54>299</y54>
			<x55>739</x55>
			<y55>294</y55>
			<x56>738</x56>
			<y56>293</y56>
			<x57>738</x57>
			<y57>292</y57>
			<x58>737</x58>
			<y58>291</y58>
			<x59>737</x59>
			<y59>290</y59>
			<x60>736</x60>
			<y60>289</y60>
			<x61>736</x61>
			<y61>288</y61>
			<x62>734</x62>
			<y62>286</y62>
			<x63>734</x63>
			<y63>285</y63>
			<x64>733</x64>
			<y64>284</y64>
			<x65>733</x65>
			<y65>280</y65>
			<x66>732</x66>
			<y66>280</y66>
			<x67>731</x67>
			<y67>279</y67>
			<x68>729</x68>
			<y68>279</y68>
			<x69>728</x69>
			<y69>278</y69>
			<x70>728</x70>
			<y70>276</y70>
			<x71>723</x71>
			<y71>276</y71>
			<x72>721</x72>
			<y72>274</y72>
			<x73>715</x73>
			<y73>274</y73>
			<x74>714</x74>
			<y74>273</y74>
			<x75>714</x75>
			<y75>272</y75>
			<x76>713</x76>
			<y76>272</y76>
			<x77>710</x77>
			<y77>275</y77>
			<x78>709</x78>
			<y78>275</y78>
		</polygon>
	</object>
	<object>
		<name>bloodstain</name>
		<pose>Unspecified</pose>
		<truncated>0</truncated>
		<difficult>0</difficult>
		<occluded>0</occluded>
		<bndbox>
			<xmin>275</xmin>
			<xmax>648</xmax>
			<ymin>255</ymin>
			<ymax>570</ymax>
		</bndbox>
		<polygon>
			<x1>326</x1>
			<y1>256</y1>
			<x2>326</x2>
			<y2>258</y2>
			<x3>325</x3>
			<y3>259</y3>
			<x4>325</x4>
			<y4>260</y4>
			<x5>324</x5>
			<y5>261</y5>
			<x6>323</x6>
			<y6>261</y6>
			<x7>322</x7>
			<y7>262</y7>
			<x8>321</x8>
			<y8>262</y8>
			<x9>320</x9>
			<y9>261</y9>
			<x10>319</x10>
			<y10>261</y10>
			<x11>318</x11>
			<y11>262</y11>
			<x12>318</x12>
			<y12>263</y12>
			<x13>317</x13>
			<y13>264</y13>
			<x14>316</x14>
			<y14>264</y14>
			<x15>315</x15>
			<y15>265</y15>
			<x16>314</x16>
			<y16>265</y16>
			<x17>313</x17>
			<y17>266</y17>
			<x18>310</x18>
			<y18>266</y18>
			<x19>309</x19>
			<y19>265</y19>
			<x20>308</x20>
			<y20>265</y20>
			<x21>306</x21>
			<y21>263</y21>
			<x22>305</x22>
			<y22>263</y22>
			<x23>304</x23>
			<y23>262</y23>
			<x24>304</x24>
			<y24>264</y24>
			<x25>303</x25>
			<y25>265</y25>
			<x26>303</x26>
			<y26>266</y26>
			<x27>304</x27>
			<y27>267</y27>
			<x28>303</x28>
			<y28>268</y28>
			<x29>303</x29>
			<y29>272</y29>
			<x30>302</x30>
			<y30>273</y30>
			<x31>302</x31>
			<y31>275</y31>
			<x32>299</x32>
			<y32>278</y32>
			<x33>298</x33>
			<y33>278</y33>
			<x34>297</x34>
			<y34>279</y34>
			<x35>291</x35>
			<y35>279</y35>
			<x36>290</x36>
			<y36>280</y36>
			<x37>290</x37>
			<y37>283</y37>
			<x38>291</x38>
			<y38>284</y38>
			<x39>290</x39>
			<y39>285</y39>
			<x40>291</x40>
			<y40>286</y40>
			<x41>291</x41>
			<y41>287</y41>
			<x42>288</x42>
			<y42>290</y42>
			<x43>285</x43>
			<y43>290</y43>
			<x44>284</x44>
			<y44>289</y44>
			<x45>283</x45>
			<y45>290</y45>
			<x46>284</x46>
			<y46>291</y46>
			<x47>283</x47>
			<y47>292</y47>
			<x48>283</x48>
			<y48>294</y48>
			<x49>282</x49>
			<y49>295</y49>
			<x50>282</x50>
			<y50>297</y50>
			<x51>281</x51>
			<y51>298</y51>
			<x52>281</x52>
			<y52>300</y52>
			<x53>280</x53>
			<y53>301</y53>
			<x54>280</x54>
			<y54>303</y54>
			<x55>279</x55>
			<y55>304</y55>
			<x56>279</x56>
			<y56>305</y56>
			<x57>278</x57>
			<y57>306</y57>
			<x58>278</x58>
			<y58>308</y58>
			<x59>277</x59>
			<y59>309</y59>
			<x60>277</x60>
			<y60>311</y60>
			<x61>276</x61>
			<y61>312</y61>
			<x62>276</x62>
			<y62>313</y62>
			<x63>275</x63>
			<y63>314</y63>
			<x64>275</x64>
			<y64>316</y64>
			<x65>274</x65>
			<y65>317</y65>
			<x66>274</x66>
			<y66>318</y66>
			<x67>275</x67>
			<y67>319</y67>
			<x68>274</x68>
			<y68>320</y68>
			<x69>274</x69>
			<y69>323</y69>
			<x70>275</x70>
			<y70>324</y70>
			<x71>274</x71>
			<y71>325</y71>
			<x72>274</x72>
			<y72>326</y72>
			<x73>275</x73>
			<y73>327</y73>
			<x74>275</x74>
			<y74>331</y74>
			<x75>276</x75>
			<y75>332</y75>
			<x76>276</x76>
			<y76>335</y76>
			<x77>277</x77>
			<y77>336</y77>
			<x78>277</x78>
			<y78>337</y78>
			<x79>278</x79>
			<y79>338</y79>
			<x80>278</x80>
			<y80>339</y80>
			<x81>279</x81>
			<y81>340</y81>
			<x82>279</x82>
			<y82>341</y82>
			<x83>280</x83>
			<y83>342</y83>
			<x84>280</x84>
			<y84>343</y84>
			<x85>281</x85>
			<y85>344</y85>
			<x86>281</x86>
			<y86>346</y86>
			<x87>282</x87>
			<y87>347</y87>
			<x88>282</x88>
			<y88>348</y88>
			<x89>283</x89>
			<y89>349</y89>
			<x90>283</x90>
			<y90>350</y90>
			<x91>285</x91>
			<y91>352</y91>
			<x92>285</x92>
			<y92>353</y92>
			<x93>286</x93>
			<y93>354</y93>
			<x94>286</x94>
			<y94>355</y94>
			<x95>287</x95>
			<y95>356</y95>
			<x96>287</x96>
			<y96>357</y96>
			<x97>288</x97>
			<y97>358</y97>
			<x98>288</x98>
			<y98>359</y98>
			<x99>289</x99>
			<y99>360</y99>
			<x100>289</x100>
			<y100>361</y100>
			<x101>290</x101>
			<y101>362</y101>
			<x102>290</x102>
			<y102>363</y102>
			<x103>291</x103>
			<y103>364</y103>
			<x104>291</x104>
			<y104>365</y104>
			<x105>293</x105>
			<y105>367</y105>
			<x106>293</x106>
			<y106>368</y106>
			<x107>295</x107>
			<y107>370</y107>
			<x108>295</x108>
			<y108>371</y108>
			<x109>297</x109>
			<y109>373</y109>
			<x110>298</x110>
			<y110>373</y110>
			<x111>299</x111>
			<y111>374</y111>
			<x112>302</x112>
			<y112>374</y112>
			<x113>303</x113>
			<y113>375</y113>
			<x114>304</x114>
			<y114>375</y114>
			<x115>311</x115>
			<y115>382</y115>
			<x116>317</x116>
			<y116>382</y116>
			<x117>318</x117>
			<y117>383</y117>
			<x118>321</x118>
			<y118>383</y118>
			<x119>323</x119>
			<y119>385</y119>
			<x120>323</x120>
			<y120>386</y120>
			<x121>324</x121>
			<y121>387</y121>
			<x122>326</x122>
			<y122>385</y122>
			<x123>332</x123>
			<y123>385</y123>
			<x124>333</x124>
			<y124>386</y124>
			<x125>334</x125>
			<y125>386</y125>
			<x126>335</x126>
			<y126>387</y126>
			<x127>336</x127>
			<y127>387</y127>
			<x128>337</x128>
			<y128>388</y128>
			<x129>338</x129>
			<y129>388</y129>
			<x130>339</x130>
			<y130>389</y130>
			<x131>340</x131>
			<y131>389</y131>
			<x132>341</x132>
			<y132>390</y132>
			<x133>342</x133>
			<y133>390</y133>
			<x134>343</x134>
			<y134>391</y134>
			<x135>346</x135>
			<y135>391</y135>
			<x136>347</x136>
			<y136>392</y136>
			<x137>367</x137>
			<y137>392</y137>
			<x138>368</x138>
			<y138>393</y138>
			<x139>369</x139>
			<y139>393</y139>
			<x140>370</x140>
			<y140>394</y140>
			<x141>371</x141>
			<y141>394</y141>
			<x142>373</x142>
			<y142>396</y142>
			<x143>374</x143>
			<y143>396</y143>
			<x144>375</x144>
			<y144>397</y144>
			<x145>376</x145>
			<y145>397</y145>
			<x146>378</x146>
			<y146>399</y146>
			<x147>379</x147>
			<y147>399</y147>
			<x148>380</x148>
			<y148>400</y148>
			<x149>381</x149>
			<y149>400</y149>
			<x150>382</x150>
			<y150>401</y150>
			<x151>383</x151>
			<y151>401</y151>
			<x152>384</x152>
			<y152>402</y152>
			<x153>393</x153>
			<y153>402</y153>
			<x154>394</x154>
			<y154>401</y154>
			<x155>395</x155>
			<y155>401</y155>
			<x156>396</x156>
			<y156>400</y156>
			<x157>398</x157>
			<y157>400</y157>
			<x158>399</x158>
			<y158>399</y158>
			<x159>400</x159>
			<y159>399</y159>
			<x160>401</x160>
			<y160>398</y160>
			<x161>403</x161>
			<y161>398</y161>
			<x162>404</x162>
			<y162>397</y162>
			<x163>405</x163>
			<y163>397</y163>
			<x164>406</x164>
			<y164>396</y164>
			<x165>408</x165>
			<y165>396</y165>
			<x166>409</x166>
			<y166>395</y166>
			<x167>410</x167>
			<y167>395</y167>
			<x168>411</x168>
			<y168>394</y168>
			<x169>412</x169>
			<y169>394</y169>
			<x170>413</x170>
			<y170>393</y170>
			<x171>414</x171>
			<y171>393</y171>
			<x172>415</x172>
			<y172>392</y172>
			<x173>417</x173>
			<y173>392</y173>
			<x174>418</x174>
			<y174>391</y174>
			<x175>423</x175>
			<y175>391</y175>
			<x176>424</x176>
			<y176>392</y176>
			<x177>425</x177>
			<y177>392</y177>
			<x178>427</x178>
			<y178>394</y178>
			<x179>427</x179>
			<y179>395</y179>
			<x180>428</x180>
			<y180>396</y180>
			<x181>428</x181>
			<y181>399</y181>
			<x182>427</x182>
			<y182>400</y182>
			<x183>427</x183>
			<y183>403</y183>
			<x184>426</x184>
			<y184>404</y184>
			<x185>426</x185>
			<y185>405</y185>
			<x186>427</x186>
			<y186>406</y186>
			<x187>430</x187>
			<y187>406</y187>
			<x188>430</x188>
			<y188>404</y188>
			<x189>431</x189>
			<y189>403</y189>
			<x190>432</x190>
			<y190>404</y190>
			<x191>432</x191>
			<y191>405</y191>
			<x192>433</x192>
			<y192>406</y192>
			<x193>433</x193>
			<y193>408</y193>
			<x194>434</x194>
			<y194>409</y194>
			<x195>434</x195>
			<y195>410</y195>
			<x196>435</x196>
			<y196>411</y196>
			<x197>435</x197>
			<y197>412</y197>
			<x198>436</x198>
			<y198>413</y198>
			<x199>436</x199>
			<y199>415</y199>
			<x200>437</x200>
			<y200>416</y200>
			<x201>437</x201>
			<y201>418</y201>
			<x202>438</x202>
			<y202>419</y202>
			<x203>438</x203>
			<y203>424</y203>
			<x204>436</x204>
			<y204>426</y204>
			<x205>435</x205>
			<y205>426</y205>
			<x206>434</x206>
			<y206>427</y206>
			<x207>433</x207>
			<y207>427</y207>
			<x208>433</x208>
			<y208>428</y208>
			<x209>432</x209>
			<y209>429</y209>
			<x210>432</x210>
			<y210>431</y210>
			<x211>433</x211>
			<y211>432</y211>
			<x212>433</x212>
			<y212>433</y212>
			<x213>434</x213>
			<y213>433</y213>
			<x214>435</x214>
			<y214>434</y214>
			<x215>436</x215>
			<y215>434</y215>
			<x216>437</x216>
			<y216>435</y216>
			<x217>438</x217>
			<y217>435</y217>
			<x218>439</x218>
			<y218>436</y218>
			<x219>439</x219>
			<y219>437</y219>
			<x220>440</x220>
			<y220>438</y220>
			<x221>440</x221>
			<y221>443</y221>
			<x222>437</x222>
			<y222>446</y222>
			<x223>436</x223>
			<y223>446</y223>
			<x224>434</x224>
			<y224>448</y224>
			<x225>433</x225>
			<y225>448</y225>
			<x226>432</x226>
			<y226>449</y226>
			<x227>431</x227>
			<y227>449</y227>
			<x228>431</x228>
			<y228>450</y228>
			<x229>430</x229>
			<y229>451</y229>
			<x230>431</x230>
			<y230>452</y230>
			<x231>430</x231>
			<y231>453</y231>
			<x232>430</x232>
			<y232>457</y232>
			<x233>429</x233>
			<y233>458</y233>
			<x234>429</x234>
			<y234>462</y234>
			<x235>428</x235>
			<y235>463</y235>
			<x236>428</x236>
			<y236>468</y236>
			<x237>427</x237>
			<y237>469</y237>
			<x238>427</x238>
			<y238>474</y238>
			<x239>426</x239>
			<y239>475</y239>
			<x240>429</x240>
			<y240>478</y240>
			<x241>429</x241>
			<y241>479</y241>
			<x242>430</x242>
			<y242>480</y242>
			<x243>430</x243>
			<y243>489</y243>
			<x244>431</x244>
			<y244>490</y244>
			<x245>430</x245>
			<y245>491</y245>
			<x246>431</x246>
			<y246>492</y246>
			<x247>431</x247>
			<y247>493</y247>
			<x248>434</x248>
			<y248>496</y248>
			<x249>434</x249>
			<y249>497</y249>
			<x250>435</x250>
			<y250>498</y250>
			<x251>435</x251>
			<y251>501</y251>
			<x252>436</x252>
			<y252>502</y252>
			<x253>436</x253>
			<y253>503</y253>
			<x254>438</x254>
			<y254>505</y254>
			<x255>438</x255>
			<y255>506</y255>
			<x256>442</x256>
			<y256>510</y256>
			<x257>442</x257>
			<y257>511</y257>
			<x258>444</x258>
			<y258>513</y258>
			<x259>444</x259>
			<y259>514</y259>
			<x260>445</x260>
			<y260>515</y260>
			<x261>445</x261>
			<y261>516</y261>
			<x262>446</x262>
			<y262>517</y262>
			<x263>446</x263>
			<y263>518</y263>
			<x264>447</x264>
			<y264>519</y264>
			<x265>447</x265>
			<y265>521</y265>
			<x266>446</x266>
			<y266>522</y266>
			<x267>441</x267>
			<y267>522</y267>
			<x268>440</x268>
			<y268>523</y268>
			<x269>437</x269>
			<y269>523</y269>
			<x270>435</x270>
			<y270>525</y270>
			<x271>434</x271>
			<y271>525</y271>
			<x272>428</x272>
			<y272>531</y272>
			<x273>428</x273>
			<y273>532</y273>
			<x274>426</x274>
			<y274>534</y274>
			<x275>426</x275>
			<y275>536</y275>
			<x276>425</x276>
			<y276>537</y276>
			<x277>425</x277>
			<y277>541</y277>
			<x278>424</x278>
			<y278>542</y278>
			<x279>424</x279>
			<y279>545</y279>
			<x280>423</x280>
			<y280>546</y280>
			<x281>423</x281>
			<y281>549</y281>
			<x282>424</x282>
			<y282>550</y282>
			<x283>423</x283>
			<y283>551</y283>
			<x284>424</x284>
			<y284>552</y284>
			<x285>424</x285>
			<y285>554</y285>
			<x286>425</x286>
			<y286>555</y286>
			<x287>425</x287>
			<y287>557</y287>
			<x288>426</x288>
			<y288>558</y288>
			<x289>426</x289>
			<y289>559</y289>
			<x290>428</x290>
			<y290>561</y290>
			<x291>429</x291>
			<y291>561</y291>
			<x292>431</x292>
			<y292>563</y292>
			<x293>432</x293>
			<y293>563</y293>
			<x294>434</x294>
			<y294>565</y294>
			<x295>434</x295>
			<y295>566</y295>
			<x296>435</x296>
			<y296>567</y296>
			<x297>439</x297>
			<y297>567</y297>
			<x298>440</x298>
			<y298>566</y298>
			<x299>442</x299>
			<y299>566</y299>
			<x300>444</x300>
			<y300>568</y300>
			<x301>445</x301>
			<y301>568</y301>
			<x302>446</x302>
			<y302>569</y302>
			<x303>452</x303>
			<y303>569</y303>
			<x304>453</x304>
			<y304>568</y304>
			<x305>455</x305>
			<y305>568</y305>
			<x306>455</x306>
			<y306>567</y306>
			<x307>458</x307>
			<y307>564</y307>
			<x308>459</x308>
			<y308>564</y308>
			<x309>460</x309>
			<y309>563</y309>
			<x310>461</x310>
			<y310>563</y310>
			<x311>462</x311>
			<y311>562</y311>
			<x312>463</x312>
			<y312>562</y312>
			<x313>464</x313>
			<y313>561</y313>
			<x314>464</x314>
			<y314>560</y314>
			<x315>465</x315>
			<y315>559</y315>
			<x316>465</x316>
			<y316>558</y316>
			<x317>466</x317>
			<y317>557</y317>
			<x318>466</x318>
			<y318>555</y318>
			<x319>467</x319>
			<y319>554</y319>
			<x320>467</x320>
			<y320>552</y320>
			<x321>468</x321>
			<y321>551</y321>
			<x322>468</x322>
			<y322>550</y322>
			<x323>469</x323>
			<y323>549</y323>
			<x324>469</x324>
			<y324>547</y324>
			<x325>470</x325>
			<y325>546</y325>
			<x326>470</x326>
			<y326>545</y326>
			<x327>469</x327>
			<y327>544</y327>
			<x328>469</x328>
			<y328>537</y328>
			<x329>468</x329>
			<y329>536</y329>
			<x330>468</x330>
			<y330>533</y330>
			<x331>467</x331>
			<y331>532</y331>
			<x332>467</x332>
			<y332>531</y332>
			<x333>466</x333>
			<y333>530</y333>
			<x334>466</x334>
			<y334>529</y334>
			<x335>467</x335>
			<y335>528</y335>
			<x336>469</x336>
			<y336>530</y336>
			<x337>470</x337>
			<y337>530</y337>
			<x338>471</x338>
			<y338>529</y338>
			<x339>472</x339>
			<y339>529</y339>
			<x340>473</x340>
			<y340>528</y340>
			<x341>484</x341>
			<y341>528</y341>
			<x342>485</x342>
			<y342>529</y342>
			<x343>489</x343>
			<y343>529</y343>
			<x344>490</x344>
			<y344>530</y344>
			<x345>491</x345>
			<y345>530</y345>
			<x346>491</x346>
			<y346>528</y346>
			<x347>493</x347>
			<y347>526</y347>
			<x348>495</x348>
			<y348>526</y348>
			<x349>496</x349>
			<y349>525</y349>
			<x350>500</x350>
			<y350>525</y350>
			<x351>501</x351>
			<y351>524</y351>
			<x352>504</x352>
			<y352>524</y352>
			<x353>505</x353>
			<y353>523</y353>
			<x354>506</x354>
			<y354>523</y354>
			<x355>507</x355>
			<y355>522</y355>
			<x356>508</x356>
			<y356>522</y356>
			<x357>509</x357>
			<y357>521</y357>
			<x358>510</x358>
			<y358>521</y358>
			<x359>511</x359>
			<y359>520</y359>
			<x360>512</x360>
			<y360>520</y360>
			<x361>513</x361>
			<y361>519</y361>
			<x362>514</x362>
			<y362>519</y362>
			<x363>515</x363>
			<y363>518</y363>
			<x364>516</x364>
			<y364>518</y364>
			<x365>518</x365>
			<y365>516</y365>
			<x366>519</x366>
			<y366>516</y366>
			<x367>520</x367>
			<y367>515</y367>
			<x368>521</x368>
			<y368>515</y368>
			<x369>523</x369>
			<y369>513</y369>
			<x370>528</x370>
			<y370>513</y370>
			<x371>530</x371>
			<y371>515</y371>
			<x372>530</x372>
			<y372>516</y372>
			<x373>531</x373>
			<y373>517</y373>
			<x374>531</x374>
			<y374>519</y374>
			<x375>532</x375>
			<y375>520</y375>
			<x376>532</x376>
			<y376>522</y376>
			<x377>534</x377>
			<y377>524</y377>
			<x378>538</x378>
			<y378>524</y378>
			<x379>541</x379>
			<y379>521</y379>
			<x380>540</x380>
			<y380>520</y380>
			<x381>536</x381>
			<y381>520</y381>
			<x382>534</x382>
			<y382>518</y382>
			<x383>534</x383>
			<y383>516</y383>
			<x384>536</x384>
			<y384>514</y384>
			<x385>538</x385>
			<y385>514</y385>
			<x386>539</x386>
			<y386>515</y386>
			<x387>541</x387>
			<y387>515</y387>
			<x388>542</x388>
			<y388>516</y388>
			<x389>544</x389>
			<y389>516</y389>
			<x390>545</x390>
			<y390>517</y390>
			<x391>547</x391>
			<y391>517</y391>
			<x392>548</x392>
			<y392>518</y392>
			<x393>549</x393>
			<y393>518</y393>
			<x394>550</x394>
			<y394>519</y394>
			<x395>551</x395>
			<y395>519</y395>
			<x396>552</x396>
			<y396>520</y396>
			<x397>553</x397>
			<y397>520</y397>
			<x398>554</x398>
			<y398>521</y398>
			<x399>555</x399>
			<y399>521</y399>
			<x400>556</x400>
			<y400>522</y400>
			<x401>557</x401>
			<y401>522</y401>
			<x402>558</x402>
			<y402>523</y402>
			<x403>559</x403>
			<y403>523</y403>
			<x404>560</x404>
			<y404>524</y404>
			<x405>565</x405>
			<y405>524</y405>
			<x406>566</x406>
			<y406>525</y406>
			<x407>569</x407>
			<y407>525</y407>
			<x408>571</x408>
			<y408>527</y408>
			<x409>571</x409>
			<y409>528</y409>
			<x410>572</x410>
			<y410>529</y410>
			<x411>572</x411>
			<y411>531</y411>
			<x412>573</x412>
			<y412>532</y412>
			<x413>573</x413>
			<y413>534</y413>
			<x414>574</x414>
			<y414>535</y414>
			<x415>574</x415>
			<y415>537</y415>
			<x416>575</x416>
			<y416>538</y416>
			<x417>575</x417>
			<y417>539</y417>
			<x418>576</x418>
			<y418>540</y418>
			<x419>576</x419>
			<y419>541</y419>
			<x420>577</x420>
			<y420>542</y420>
			<x421>577</x421>
			<y421>543</y421>
			<x422>578</x422>
			<y422>544</y422>
			<x423>578</x423>
			<y423>545</y423>
			<x424>579</x424>
			<y424>546</y424>
			<x425>579</x425>
			<y425>548</y425>
			<x426>580</x426>
			<y426>549</y426>
			<x427>580</x427>
			<y427>552</y427>
			<x428>581</x428>
			<y428>553</y428>
			<x429>584</x429>
			<y429>553</y429>
			<x430>585</x430>
			<y430>554</y430>
			<x431>589</x431>
			<y431>554</y431>
			<x432>589</x432>
			<y432>553</y432>
			<x433>588</x433>
			<y433>552</y433>
			<x434>588</x434>
			<y434>551</y434>
			<x435>587</x435>
			<y435>550</y435>
			<x436>587</x436>
			<y436>549</y436>
			<x437>589</x437>
			<y437>547</y437>
			<x438>590</x438>
			<y438>547</y438>
			<x439>591</x439>
			<y439>546</y439>
			<x440>592</x440>
			<y440>546</y440>
			<x441>594</x441>
			<y441>544</y441>
			<x442>594</x442>
			<y442>541</y442>
			<x443>589</x443>
			<y443>536</y443>
			<x444>588</x444>
			<y444>536</y444>
			<x445>582</x445>
			<y445>530</y445>
			<x446>582</x446>
			<y446>529</y446>
			<x447>583</x447>
			<y447>528</y447>
			<x448>583</x448>
			<y448>527</y448>
			<x449>585</x449>
			<y449>525</y449>
			<x450>587</x450>
			<y450>525</y450>
			<x451>588</x451>
			<y451>526</y451>
			<x452>588</x452>
			<y452>528</y452>
			<x453>590</x453>
			<y453>530</y453>
			<x454>591</x454>
			<y454>530</y454>
			<x455>592</x455>
			<y455>531</y455>
			<x456>594</x456>
			<y456>531</y456>
			<x457>596</x457>
			<y457>529</y457>
			<x458>596</x458>
			<y458>528</y458>
			<x459>593</x459>
			<y459>525</y459>
			<x460>590</x460>
			<y460>525</y460>
			<x461>589</x461>
			<y461>524</y461>
			<x462>589</x462>
			<y462>522</y462>
			<x463>591</x463>
			<y463>520</y463>
			<x464>600</x464>
			<y464>520</y464>
			<x465>601</x465>
			<y465>519</y465>
			<x466>602</x466>
			<y466>519</y466>
			<x467>603</x467>
			<y467>518</y467>
			<x468>603</x468>
			<y468>517</y468>
			<x469>605</x469>
			<y469>515</y469>
			<x470>605</x470>
			<y470>514</y470>
			<x471>606</x471>
			<y471>513</y471>
			<x472>606</x472>
			<y472>512</y472>
			<x473>610</x473>
			<y473>508</y473>
			<x474>612</x474>
			<y474>508</y474>
			<x475>613</x475>
			<y475>509</y475>
			<x476>616</x476>
			<y476>509</y476>
			<x477>617</x477>
			<y477>508</y477>
			<x478>621</x478>
			<y478>508</y478>
			<x479>622</x479>
			<y479>507</y479>
			<x480>627</x480>
			<y480>507</y480>
			<x481>628</x481>
			<y481>508</y481>
			<x482>629</x482>
			<y482>508</y482>
			<x483>630</x483>
			<y483>509</y483>
			<x484>630</x484>
			<y484>505</y484>
			<x485>629</x485>
			<y485>504</y485>
			<x486>629</x486>
			<y486>503</y486>
			<x487>628</x487>
			<y487>502</y487>
			<x488>628</x488>
			<y488>494</y488>
			<x489>630</x489>
			<y489>492</y489>
			<x490>633</x490>
			<y490>492</y490>
			<x491>634</x491>
			<y491>491</y491>
			<x492>635</x492>
			<y492>491</y492>
			<x493>636</x493>
			<y493>492</y493>
			<x494>637</x494>
			<y494>492</y494>
			<x495>638</x495>
			<y495>493</y495>
			<x496>639</x496>
			<y496>493</y496>
			<x497>640</x497>
			<y497>494</y497>
			<x498>642</x498>
			<y498>494</y498>
			<x499>642</x499>
			<y499>490</y499>
			<x500>641</x500>
			<y500>489</y500>
			<x501>641</x501>
			<y501>478</y501>
			<x502>643</x502>
			<y502>476</y502>
			<x503>645</x503>
			<y503>476</y503>
			<x504>646</x504>
			<y504>475</y504>
			<x505>647</x505>
			<y505>475</y505>
			<x506>647</x506>
			<y506>474</y506>
			<x507>646</x507>
			<y507>473</y507>
			<x508>646</x508>
			<y508>472</y508>
			<x509>643</x509>
			<y509>472</y509>
			<x510>641</x510>
			<y510>470</y510>
			<x511>641</x511>
			<y511>468</y511>
			<x512>640</x512>
			<y512>467</y512>
			<x513>640</x513>
			<y513>464</y513>
			<x514>639</x514>
			<y514>463</y514>
			<x515>639</x515>
			<y515>461</y515>
			<x516>638</x516>
			<y516>462</y516>
			<x517>637</x517>
			<y517>462</y517>
			<x518>635</x518>
			<y518>464</y518>
			<x519>634</x519>
			<y519>464</y519>
			<x520>633</x520>
			<y520>465</y520>
			<x521>630</x521>
			<y521>465</y521>
			<x522>629</x522>
			<y522>464</y522>
			<x523>629</x523>
			<y523>463</y523>
			<x524>628</x524>
			<y524>462</y524>
			<x525>628</x525>
			<y525>456</y525>
			<x526>629</x526>
			<y526>455</y526>
			<x527>629</x527>
			<y527>454</y527>
			<x528>630</x528>
			<y528>453</y528>
			<x529>630</x529>
			<y529>445</y529>
			<x530>631</x530>
			<y530>444</y530>
			<x531>631</x531>
			<y531>434</y531>
			<x532>632</x532>
			<y532>433</y532>
			<x533>632</x533>
			<y533>430</y533>
			<x534>633</x534>
			<y534>429</y534>
			<x535>633</x535>
			<y535>428</y535>
			<x536>634</x536>
			<y536>427</y536>
			<x537>636</x537>
			<y537>427</y537>
			<x538>637</x538>
			<y538>426</y538>
			<x539>639</x539>
			<y539>426</y539>
			<x540>640</x540>
			<y540>427</y540>
			<x541>641</x541>
			<y541>427</y541>
			<x542>642</x542>
			<y542>428</y542>
			<x543>642</x543>
			<y543>429</y543>
			<x544>643</x544>
			<y544>430</y544>
			<x545>644</x545>
			<y545>429</y545>
			<x546>644</x546>
			<y546>427</y546>
			<x547>645</x547>
			<y547>426</y547>
			<x548>646</x548>
			<y548>426</y548>
			<x549>647</x549>
			<y549>425</y549>
			<x550>646</x550>
			<y550>424</y550>
			<x551>646</x551>
			<y551>423</y551>
			<x552>645</x552>
			<y552>423</y552>
			<x553>644</x553>
			<y553>422</y553>
			<x554>643</x554>
			<y554>422</y554>
			<x555>642</x555>
			<y555>423</y555>
			<x556>640</x556>
			<y556>421</y556>
			<x557>640</x557>
			<y557>420</y557>
			<x558>638</x558>
			<y558>418</y558>
			<x559>633</x559>
			<y559>418</y559>
			<x560>633</x560>
			<y560>419</y560>
			<x561>629</x561>
			<y561>423</y561>
			<x562>629</x562>
			<y562>424</y562>
			<x563>628</x563>
			<y563>425</y563>
			<x564>625</x564>
			<y564>425</y564>
			<x565>625</x565>
			<y565>426</y565>
			<x566>624</x566>
			<y566>427</y566>
			<x567>624</x567>
			<y567>428</y567>
			<x568>623</x568>
			<y568>429</y568>
			<x569>623</x569>
			<y569>432</y569>
			<x570>622</x570>
			<y570>433</y570>
			<x571>622</x571>
			<y571>434</y571>
			<x572>621</x572>
			<y572>435</y572>
			<x573>621</x573>
			<y573>436</y573>
			<x574>618</x574>
			<y574>439</y574>
			<x575>617</x575>
			<y575>439</y575>
			<x576>616</x576>
			<y576>440</y576>
			<x577>615</x577>
			<y577>440</y577>
			<x578>614</x578>
			<y578>439</y578>
			<x579>611</x579>
			<y579>439</y579>
			<x580>610</x580>
			<y580>438</y580>
			<x581>610</x581>
			<y581>437</y581>
			<x582>609</x582>
			<y582>437</y582>
			<x583>608</x583>
			<y583>436</y583>
			<x584>606</x584>
			<y584>436</y584>
			<x585>605</x585>
			<y585>435</y585>
			<x586>602</x586>
			<y586>435</y586>
			<x587>600</x587>
			<y587>433</y587>
			<x588>600</x588>
			<y588>432</y588>
			<x589>599</x589>
			<y589>432</y589>
			<x590>598</x590>
			<y590>433</y590>
			<x591>597</x591>
			<y591>433</y591>
			<x592>596</x592>
			<y592>434</y592>
			<x593>591</x593>
			<y593>429</y593>
			<x594>591</x594>
			<y594>428</y594>
			<x595>588</x595>
			<y595>425</y595>
			<x596>588</x596>
			<y596>422</y596>
			<x597>587</x597>
			<y597>421</y597>
			<x598>587</x598>
			<y598>414</y598>
			<x599>581</x599>
			<y599>414</y599>
			<x600>579</x600>
			<y600>412</y600>
			<x601>579</x601>
			<y601>411</y601>
			<x602>578</x602>
			<y602>410</y602>
			<x603>578</x603>
			<y603>406</y603>
			<x604>579</x604>
			<y604>405</y604>
			<x605>584</x605>
			<y605>405</y605>
			<x606>585</x606>
			<y606>406</y606>
			<x607>586</x607>
			<y607>406</y607>
			<x608>587</x608>
			<y608>407</y608>
			<x609>588</x609>
			<y609>407</y609>
			<x610>589</x610>
			<y610>408</y610>
			<x611>590</x611>
			<y611>408</y611>
			<x612>591</x612>
			<y612>409</y612>
			<x613>592</x613>
			<y613>409</y613>
			<x614>593</x614>
			<y614>408</y614>
			<x615>599</x615>
			<y615>408</y615>
			<x616>600</x616>
			<y616>409</y616>
			<x617>604</x617>
			<y617>409</y617>
			<x618>604</x618>
			<y618>408</y618>
			<x619>603</x619>
			<y619>407</y619>
			<x620>603</x620>
			<y620>404</y620>
			<x621>604</x621>
			<y621>403</y621>
			<x622>605</x622>
			<y622>403</y622>
			<x623>607</x623>
			<y623>405</y623>
			<x624>607</x624>
			<y624>408</y624>
			<x625>608</x625>
			<y625>409</y625>
			<x626>612</x626>
			<y626>409</y626>
			<x627>613</x627>
			<y627>408</y627>
			<x628>614</x628>
			<y628>408</y628>
			<x629>614</x629>
			<y629>405</y629>
			<x630>610</x630>
			<y630>401</y630>
			<x631>610</x631>
			<y631>400</y631>
			<x632>613</x632>
			<y632>397</y632>
			<x633>614</x633>
			<y633>397</y633>
			<x634>615</x634>
			<y634>396</y634>
			<x635>616</x635>
			<y635>396</y635>
			<x636>618</x636>
			<y636>394</y636>
			<x637>618</x637>
			<y637>390</y637>
			<x638>617</x638>
			<y638>389</y638>
			<x639>617</x639>
			<y639>388</y639>
			<x640>616</x640>
			<y640>387</y640>
			<x641>616</x641>
			<y641>386</y641>
			<x642>615</x642>
			<y642>385</y642>
			<x643>615</x643>
			<y643>384</y643>
			<x644>614</x644>
			<y644>383</y644>
			<x645>614</x645>
			<y645>379</y645>
			<x646>615</x646>
			<y646>378</y646>
			<x647>615</x647>
			<y647>376</y647>
			<x648>613</x648>
			<y648>374</y648>
			<x649>612</x649>
			<y649>374</y649>
			<x650>611</x650>
			<y650>373</y650>
			<x651>610</x651>
			<y651>373</y651>
			<x652>609</x652>
			<y652>372</y652>
			<x653>609</x653>
			<y653>369</y653>
			<x654>605</x654>
			<y654>369</y654>
			<x655>603</x655>
			<y655>367</y655>
			<x656>603</x656>
			<y656>366</y656>
			<x657>598</x657>
			<y657>366</y657>
			<x658>597</x658>
			<y658>365</y658>
			<x659>597</x659>
			<y659>364</y659>
			<x660>596</x660>
			<y660>364</y660>
			<x661>595</x661>
			<y661>363</y661>
			<x662>594</x662>
			<y662>364</y662>
			<x663>594</x663>
			<y663>365</y663>
			<x664>593</x664>
			<y664>366</y664>
			<x665>592</x665>
			<y665>366</y665>
			<x666>591</x666>
			<y666>365</y666>
			<x667>591</x667>
			<y667>364</y667>
			<x668>590</x668>
			<y668>363</y668>
			<x669>590</x669>
			<y669>362</y669>
			<x670>586</x670>
			<y670>362</y670>
			<x671>585</x671>
			<y671>363</y671>
			<x672>585</x672>
			<y672>364</y672>
			<x673>584</x673>
			<y673>365</y673>
			<x674>584</x674>
			<y674>366</y674>
			<x675>583</x675>
			<y675>367</y675>
			<x676>583</x676>
			<y676>368</y676>
			<x677>582</x677>
			<y677>369</y677>
			<x678>582</x678>
			<y678>370</y678>
			<x679>581</x679>
			<y679>371</y679>
			<x680>578</x680>
			<y680>371</y680>
			<x681>577</x681>
			<y681>372</y681>
			<x682>578</x682>
			<y682>373</y682>
			<x683>578</x683>
			<y683>374</y683>
			<x684>577</x684>
			<y684>375</y684>
			<x685>575</x685>
			<y685>375</y685>
			<x686>574</x686>
			<y686>376</y686>
			<x687>574</x687>
			<y687>377</y687>
			<x688>575</x688>
			<y688>378</y688>
			<x689>575</x689>
			<y689>381</y689>
			<x690>574</x690>
			<y690>382</y690>
			<x691>571</x691>
			<y691>382</y691>
			<x692>570</x692>
			<y692>381</y692>
			<x693>570</x693>
			<y693>380</y693>
			<x694>571</x694>
			<y694>379</y694>
			<x695>571</x695>
			<y695>376</y695>
			<x696>568</x696>
			<y696>376</y696>
			<x697>565</x697>
			<y697>373</y697>
			<x698>565</x698>
			<y698>368</y698>
			<x699>562</x699>
			<y699>368</y699>
			<x700>560</x700>
			<y700>366</y700>
			<x701>555</x701>
			<y701>366</y701>
			<x702>553</x702>
			<y702>364</y702>
			<x703>553</x703>
			<y703>358</y703>
			<x704>551</x704>
			<y704>358</y704>
			<x705>550</x705>
			<y705>357</y705>
			<x706>550</x706>
			<y706>351</y706>
			<x707>546</x707>
			<y707>351</y707>
			<x708>546</x708>
			<y708>352</y708>
			<x709>545</x709>
			<y709>353</y709>
			<x710>545</x710>
			<y710>355</y710>
			<x711>544</x711>
			<y711>356</y711>
			<x712>544</x712>
			<y712>357</y712>
			<x713>541</x713>
			<y713>360</y713>
			<x714>537</x714>
			<y714>360</y714>
			<x715>531</x715>
			<y715>354</y715>
			<x716>531</x716>
			<y716>351</y716>
			<x717>530</x717>
			<y717>350</y717>
			<x718>530</x718>
			<y718>345</y718>
			<x719>531</x719>
			<y719>344</y719>
			<x720>531</x720>
			<y720>343</y720>
			<x721>525</x721>
			<y721>343</y721>
			<x722>524</x722>
			<y722>342</y722>
			<x723>524</x723>
			<y723>334</y723>
			<x724>525</x724>
			<y724>333</y724>
			<x725>525</x725>
			<y725>325</y725>
			<x726>527</x726>
			<y726>323</y726>
			<x727>527</x727>
			<y727>322</y727>
			<x728>530</x728>
			<y728>319</y728>
			<x729>531</x729>
			<y729>319</y729>
			<x730>534</x730>
			<y730>316</y730>
			<x731>533</x731>
			<y731>315</y731>
			<x732>533</x732>
			<y732>307</y732>
			<x733>534</x733>
			<y733>306</y733>
			<x734>534</x734>
			<y734>305</y734>
			<x735>536</x735>
			<y735>303</y735>
			<x736>536</x736>
			<y736>302</y736>
			<x737>537</x737>
			<y737>301</y737>
			<x738>537</x738>
			<y738>300</y738>
			<x739>536</x739>
			<y739>299</y739>
			<x740>536</x740>
			<y740>298</y740>
			<x741>535</x741>
			<y741>297</y741>
			<x742>535</x742>
			<y742>296</y742>
			<x743>533</x743>
			<y743>296</y743>
			<x744>533</x744>
			<y744>297</y744>
			<x745>532</x745>
			<y745>298</y745>
			<x746>531</x746>
			<y746>298</y746>
			<x747>530</x747>
			<y747>299</y747>
			<x748>528</x748>
			<y748>297</y748>
			<x749>519</x749>
			<y749>297</y749>
			<x750>518</x750>
			<y750>296</y750>
			<x751>517</x751>
			<y751>296</y751>
			<x752>516</x752>
			<y752>295</y752>
			<x753>515</x753>
			<y753>296</y753>
			<x754>514</x754>
			<y754>296</y754>
			<x755>508</x755>
			<y755>302</y755>
			<x756>507</x756>
			<y756>302</y756>
			<x757>506</x757>
			<y757>303</y757>
			<x758>502</x758>
			<y758>303</y758>
			<x759>501</x759>
			<y759>302</y759>
			<x760>499</x760>
			<y760>302</y760>
			<x761>497</x761>
			<y761>304</y761>
			<x762>495</x762>
			<y762>304</y762>
			<x763>494</x763>
			<y763>303</y763>
			<x764>494</x764>
			<y764>302</y764>
			<x765>493</x765>
			<y765>301</y765>
			<x766>493</x766>
			<y766>300</y766>
			<x767>492</x767>
			<y767>299</y767>
			<x768>492</x768>
			<y768>294</y768>
			<x769>491</x769>
			<y769>293</y769>
			<x770>491</x770>
			<y770>292</y770>
			<x771>490</x771>
			<y771>292</y771>
			<x772>489</x772>
			<y772>291</y772>
			<x773>488</x773>
			<y773>291</y773>
			<x774>488</x774>
			<y774>292</y774>
			<x775>487</x775>
			<y775>293</y775>
			<x776>487</x776>
			<y776>294</y776>
			<x777>488</x777>
			<y777>295</y777>
			<x778>487</x778>
			<y778>296</y778>
			<x779>488</x779>
			<y779>297</y779>
			<x780>488</x780>
			<y780>299</y780>
			<x781>487</x781>
			<y781>300</y781>
			<x782>485</x782>
			<y782>298</y782>
			<x783>485</x783>
			<y783>297</y783>
			<x784>484</x784>
			<y784>296</y784>
			<x785>484</x785>
			<y785>295</y785>
			<x786>482</x786>
			<y786>293</y786>
			<x787>482</x787>
			<y787>290</y787>
			<x788>481</x788>
			<y788>289</y788>
			<x789>481</x789>
			<y789>288</y789>
			<x790>473</x790>
			<y790>288</y790>
			<x791>473</x791>
			<y791>290</y791>
			<x792>477</x792>
			<y792>290</y792>
			<x793>478</x793>
			<y793>291</y793>
			<x794>478</x794>
			<y794>292</y794>
			<x795>479</x795>
			<y795>293</y795>
			<x796>479</x796>
			<y796>297</y796>
			<x797>478</x797>
			<y797>298</y797>
			<x798>472</x798>
			<y798>298</y798>
			<x799>468</x799>
			<y799>294</y799>
			<x800>468</x800>
			<y800>293</y800>
			<x801>466</x801>
			<y801>291</y801>
			<x802>466</x802>
			<y802>290</y802>
			<x803>465</x803>
			<y803>289</y803>
			<x804>465</x804>
			<y804>287</y804>
			<x805>464</x805>
			<y805>287</y805>
			<x806>463</x806>
			<y806>286</y806>
			<x807>462</x807>
			<y807>287</y807>
			<x808>462</x808>
			<y808>291</y808>
			<x809>459</x809>
			<y809>294</y809>
			<x810>458</x810>
			<y810>294</y810>
			<x811>456</x811>
			<y811>296</y811>
			<x812>455</x812>
			<y812>296</y812>
			<x813>454</x813>
			<y813>297</y813>
			<x814>449</x814>
			<y814>297</y814>
			<x815>448</x815>
			<y815>296</y815>
			<x816>444</x816>
			<y816>296</y816>
			<x817>443</x817>
			<y817>295</y817>
			<x818>441</x818>
			<y818>295</y818>
			<x819>440</x819>
			<y819>296</y819>
			<x820>439</x820>
			<y820>296</y820>
			<x821>439</x821>
			<y821>297</y821>
			<x822>438</x822>
			<y822>298</y822>
			<x823>438</x823>
			<y823>299</y823>
			<x824>436</x824>
			<y824>301</y824>
			<x825>436</x825>
			<y825>302</y825>
			<x826>430</x826>
			<y826>308</y826>
			<x827>426</x827>
			<y827>308</y827>
			<x828>425</x828>
			<y828>307</y828>
			<x829>424</x829>
			<y829>307</y829>
			<x830>424</x830>
			<y830>308</y830>
			<x831>423</x831>
			<y831>309</y831>
			<x832>423</x832>
			<y832>310</y832>
			<x833>422</x833>
			<y833>311</y833>
			<x834>421</x834>
			<y834>311</y834>
			<x835>420</x835>
			<y835>312</y835>
			<x836>418</x836>
			<y836>312</y836>
			<x837>417</x837>
			<y837>311</y837>
			<x838>415</x838>
			<y838>311</y838>
			<x839>414</x839>
			<y839>310</y839>
			<x840>413</x840>
			<y840>310</y840>
			<x841>409</x841>
			<y841>306</y841>
			<x842>408</x842>
			<y842>306</y842>
			<x843>406</x843>
			<y843>304</y843>
			<x844>406</x844>
			<y844>302</y844>
			<x845>405</x845>
			<y845>301</y845>
			<x846>405</x846>
			<y846>294</y846>
			<x847>402</x847>
			<y847>291</y847>
			<x848>401</x848>
			<y848>291</y848>
			<x849>399</x849>
			<y849>289</y849>
			<x850>399</x850>
			<y850>287</y850>
			<x851>398</x851>
			<y851>286</y851>
			<x852>398</x852>
			<y852>281</y852>
			<x853>397</x853>
			<y853>280</y853>
			<x854>396</x854>
			<y854>280</y854>
			<x855>394</x855>
			<y855>278</y855>
			<x856>393</x856>
			<y856>278</y856>
			<x857>392</x857>
			<y857>277</y857>
			<x858>392</x858>
			<y858>276</y858>
			<x859>391</x859>
			<y859>275</y859>
			<x860>391</x860>
			<y860>273</y860>
			<x861>390</x861>
			<y861>272</y861>
			<x862>390</x862>
			<y862>271</y862>
			<x863>389</x863>
			<y863>271</y863>
			<x864>388</x864>
			<y864>270</y864>
			<x865>387</x865>
			<y865>270</y865>
			<x866>386</x866>
			<y866>269</y866>
			<x867>386</x867>
			<y867>268</y867>
			<x868>376</x868>
			<y868>268</y868>
			<x869>372</x869>
			<y869>264</y869>
			<x870>372</x870>
			<y870>263</y870>
			<x871>368</x871>
			<y871>259</y871>
			<x872>368</x872>
			<y872>258</y872>
			<x873>367</x873>
			<y873>258</y873>
			<x874>366</x874>
			<y874>257</y874>
			<x875>364</x875>
			<y875>257</y875>
			<x876>364</x876>
			<y876>258</y876>
			<x877>363</x877>
			<y877>259</y877>
			<x878>361</x878>
			<y878>259</y878>
			<x879>360</x879>
			<y879>258</y879>
			<x880>359</x880>
			<y880>258</y880>
			<x881>358</x881>
			<y881>257</y881>
			<x882>356</x882>
			<y882>257</y882>
			<x883>355</x883>
			<y883>256</y883>
			<x884>352</x884>
			<y884>256</y884>
			<x885>351</x885>
			<y885>257</y885>
			<x886>350</x886>
			<y886>257</y886>
			<x887>349</x887>
			<y887>258</y887>
			<x888>347</x888>
			<y888>258</y888>
			<x889>343</x889>
			<y889>254</y889>
			<x890>342</x890>
			<y890>254</y890>
			<x891>341</x891>
			<y891>255</y891>
			<x892>341</x892>
			<y892>256</y892>
			<x893>340</x893>
			<y893>257</y893>
			<x894>339</x894>
			<y894>257</y894>
			<x895>338</x895>
			<y895>258</y895>
			<x896>337</x896>
			<y896>258</y896>
			<x897>336</x897>
			<y897>259</y897>
			<x898>333</x898>
			<y898>259</y898>
			<x899>332</x899>
			<y899>258</y899>
			<x900>331</x900>
			<y900>258</y900>
			<x901>328</x901>
			<y901>255</y901>
			<x902>328</x902>
			<y902>254</y902>
			<x903>327</x903>
			<y903>254</y903>
			<x904>327</x904>
			<y904>255</y904>
			<x905>326</x905>
			<y905>256</y905>
		</polygon>
	</object>
	<object>
		<name>bloodstain</name>
		<pose>Unspecified</pose>
		<truncated>0</truncated>
		<difficult>0</difficult>
		<occluded>0</occluded>
		<bndbox>
			<xmin>585</xmin>
			<xmax>644</xmax>
			<ymin>558</ymin>
			<ymax>607</ymax>
		</bndbox>
		<polygon>
			<x1>621</x1>
			<y1>559</y1>
			<x2>617</x2>
			<y2>559</y2>
			<x3>616</x3>
			<y3>558</y3>
			<x4>615</x4>
			<y4>558</y4>
			<x5>614</x5>
			<y5>559</y5>
			<x6>610</x6>
			<y6>559</y6>
			<x7>609</x7>
			<y7>560</y7>
			<x8>603</x8>
			<y8>560</y8>
			<x9>603</x9>
			<y9>562</y9>
			<x10>602</x10>
			<y10>563</y10>
			<x11>602</x11>
			<y11>565</y11>
			<x12>601</x12>
			<y12>566</y12>
			<x13>601</x13>
			<y13>567</y13>
			<x14>599</x14>
			<y14>569</y14>
			<x15>599</x15>
			<y15>570</y15>
			<x16>598</x16>
			<y16>571</y16>
			<x17>597</x17>
			<y17>571</y17>
			<x18>596</x18>
			<y18>572</y18>
			<x19>595</x19>
			<y19>571</y19>
			<x20>594</x20>
			<y20>571</y20>
			<x21>591</x21>
			<y21>568</y21>
			<x22>591</x22>
			<y22>567</y22>
			<x23>585</x23>
			<y23>567</y23>
			<x24>585</x24>
			<y24>568</y24>
			<x25>584</x25>
			<y25>569</y25>
			<x26>585</x26>
			<y26>570</y26>
			<x27>585</x27>
			<y27>572</y27>
			<x28>588</x28>
			<y28>575</y28>
			<x29>589</x29>
			<y29>575</y29>
			<x30>591</x30>
			<y30>577</y30>
			<x31>592</x31>
			<y31>577</y31>
			<x32>594</x32>
			<y32>579</y32>
			<x33>594</x33>
			<y33>582</y33>
			<x34>593</x34>
			<y34>583</y34>
			<x35>593</x35>
			<y35>586</y35>
			<x36>595</x36>
			<y36>588</y36>
			<x37>595</x37>
			<y37>589</y37>
			<x38>596</x38>
			<y38>590</y38>
			<x39>596</x39>
			<y39>591</y39>
			<x40>597</x40>
			<y40>592</y40>
			<x41>597</x41>
			<y41>593</y41>
			<x42>598</x42>
			<y42>594</y42>
			<x43>598</x43>
			<y43>595</y43>
			<x44>599</x44>
			<y44>596</y44>
			<x45>599</x45>
			<y45>597</y45>
			<x46>604</x46>
			<y46>602</y46>
			<x47>605</x47>
			<y47>602</y47>
			<x48>606</x48>
			<y48>603</y48>
			<x49>608</x49>
			<y49>603</y49>
			<x50>609</x50>
			<y50>604</y50>
			<x51>612</x51>
			<y51>604</y51>
			<x52>613</x52>
			<y52>605</y52>
			<x53>614</x53>
			<y53>605</y53>
			<x54>615</x54>
			<y54>606</y54>
			<x55>620</x55>
			<y55>606</y55>
			<x56>621</x56>
			<y56>605</y56>
			<x57>621</x57>
			<y57>604</y57>
			<x58>622</x58>
			<y58>603</y58>
			<x59>624</x59>
			<y59>603</y59>
			<x60>625</x60>
			<y60>602</y60>
			<x61>626</x61>
			<y61>602</y61>
			<x62>628</x62>
			<y62>604</y62>
			<x63>633</x63>
			<y63>604</y63>
			<x64>633</x64>
			<y64>602</y64>
			<x65>632</x65>
			<y65>601</y65>
			<x66>632</x66>
			<y66>599</y66>
			<x67>639</x67>
			<y67>592</y67>
			<x68>639</x68>
			<y68>589</y68>
			<x69>640</x69>
			<y69>588</y69>
			<x70>641</x70>
			<y70>588</y70>
			<x71>642</x71>
			<y71>587</y71>
			<x72>641</x72>
			<y72>586</y72>
			<x73>641</x73>
			<y73>583</y73>
			<x74>642</x74>
			<y74>582</y74>
			<x75>642</x75>
			<y75>581</y75>
			<x76>643</x76>
			<y76>580</y76>
			<x77>643</x77>
			<y77>576</y77>
			<x78>642</x78>
			<y78>575</y78>
			<x79>640</x79>
			<y79>575</y79>
			<x80>639</x80>
			<y80>574</y80>
			<x81>639</x81>
			<y81>570</y81>
			<x82>638</x82>
			<y82>569</y82>
			<x83>638</x83>
			<y83>568</y83>
			<x84>634</x84>
			<y84>564</y84>
			<x85>633</x85>
			<y85>564</y85>
			<x86>632</x86>
			<y86>563</y86>
			<x87>631</x87>
			<y87>563</y87>
			<x88>629</x88>
			<y88>561</y88>
			<x89>628</x89>
			<y89>561</y89>
			<x90>626</x90>
			<y90>559</y90>
			<x91>625</x91>
			<y91>559</y91>
			<x92>624</x92>
			<y92>558</y92>
			<x93>623</x93>
			<y93>558</y93>
			<x94>622</x94>
			<y94>557</y94>
			<x95>622</x95>
			<y95>558</y95>
			<x96>621</x96>
			<y96>559</y96>
		</polygon>
	</object>
	<object>
		<name>bloodstain</name>
		<pose>Unspecified</pose>
		<truncated>0</truncated>
		<difficult>0</difficult>
		<occluded>0</occluded>
		<bndbox>
			<xmin>460</xmin>
			<xmax>499</xmax>
			<ymin>626</ymin>
			<ymax>667</ymax>
		</bndbox>
		<polygon>
			<x1>474</x1>
			<y1>626</y1>
			<x2>473</x2>
			<y2>627</y2>
			<x3>471</x3>
			<y3>627</y3>
			<x4>470</x4>
			<y4>628</y4>
			<x5>469</x5>
			<y5>628</y5>
			<x6>468</x6>
			<y6>629</y6>
			<x7>467</x7>
			<y7>629</y7>
			<x8>466</x8>
			<y8>630</y8>
			<x9>464</x9>
			<y9>630</y9>
			<x10>463</x10>
			<y10>629</y10>
			<x11>462</x11>
			<y11>629</y11>
			<x12>462</x12>
			<y12>630</y12>
			<x13>461</x13>
			<y13>631</y13>
			<x14>461</x14>
			<y14>632</y14>
			<x15>460</x15>
			<y15>633</y15>
			<x16>460</x16>
			<y16>637</y16>
			<x17>459</x17>
			<y17>638</y17>
			<x18>459</x18>
			<y18>639</y18>
			<x19>460</x19>
			<y19>640</y19>
			<x20>459</x20>
			<y20>641</y20>
			<x21>459</x21>
			<y21>644</y21>
			<x22>460</x22>
			<y22>645</y22>
			<x23>459</x23>
			<y23>646</y23>
			<x24>459</x24>
			<y24>648</y24>
			<x25>460</x25>
			<y25>649</y25>
			<x26>460</x26>
			<y26>654</y26>
			<x27>461</x27>
			<y27>655</y27>
			<x28>461</x28>
			<y28>658</y28>
			<x29>462</x29>
			<y29>659</y29>
			<x30>462</x30>
			<y30>660</y30>
			<x31>463</x31>
			<y31>660</y31>
			<x32>464</x32>
			<y32>659</y32>
			<x33>466</x33>
			<y33>659</y33>
			<x34>470</x34>
			<y34>663</y34>
			<x35>471</x35>
			<y35>663</y35>
			<x36>472</x36>
			<y36>664</y36>
			<x37>473</x37>
			<y37>664</y37>
			<x38>474</x38>
			<y38>665</y38>
			<x39>476</x39>
			<y39>665</y39>
			<x40>477</x40>
			<y40>666</y40>
			<x41>480</x41>
			<y41>666</y41>
			<x42>481</x42>
			<y42>665</y42>
			<x43>483</x43>
			<y43>665</y43>
			<x44>484</x44>
			<y44>664</y44>
			<x45>485</x45>
			<y45>664</y45>
			<x46>486</x46>
			<y46>663</y46>
			<x47>487</x47>
			<y47>663</y47>
			<x48>488</x48>
			<y48>662</y48>
			<x49>489</x49>
			<y49>662</y49>
			<x50>490</x50>
			<y50>661</y50>
			<x51>491</x51>
			<y51>661</y51>
			<x52>493</x52>
			<y52>659</y52>
			<x53>493</x53>
			<y53>658</y53>
			<x54>494</x54>
			<y54>657</y54>
			<x55>494</x55>
			<y55>656</y55>
			<x56>495</x56>
			<y56>655</y56>
			<x57>495</x57>
			<y57>653</y57>
			<x58>496</x58>
			<y58>652</y58>
			<x59>496</x59>
			<y59>650</y59>
			<x60>497</x60>
			<y60>649</y60>
			<x61>497</x61>
			<y61>648</y61>
			<x62>498</x62>
			<y62>647</y62>
			<x63>498</x63>
			<y63>644</y63>
			<x64>497</x64>
			<y64>643</y64>
			<x65>497</x65>
			<y65>640</y65>
			<x66>496</x66>
			<y66>639</y66>
			<x67>496</x67>
			<y67>638</y67>
			<x68>495</x68>
			<y68>637</y68>
			<x69>495</x69>
			<y69>636</y69>
			<x70>493</x70>
			<y70>634</y70>
			<x71>493</x71>
			<y71>633</y71>
			<x72>489</x72>
			<y72>629</y72>
			<x73>488</x73>
			<y73>629</y73>
			<x74>485</x74>
			<y74>626</y74>
			<x75>484</x75>
			<y75>626</y75>
			<x76>483</x76>
			<y76>625</y76>
			<x77>476</x77>
			<y77>625</y77>
			<x78>475</x78>
			<y78>626</y78>
			<x79>474</x79>
			<y79>626</y79>
		</polygon>
	</object>
</annotation>
