<annotation>
	<folder></folder>
	<filename>5_DALL-E-2022-12-01-13-10-46-Stains-of-blood-on-the-floor_png.rf.79f58a0396fab247e35acd78b3361ee1.jpg</filename>
	<path>5_DALL-E-2022-12-01-13-10-46-Stains-of-blood-on-the-floor_png.rf.79f58a0396fab247e35acd78b3361ee1.jpg</path>
	<source>
		<database>roboflow.com</database>
	</source>
	<size>
		<width>1024</width>
		<height>1024</height>
		<depth>3</depth>
	</size>
	<segmented>0</segmented>
	<object>
		<name>bloodstain</name>
		<pose>Unspecified</pose>
		<truncated>0</truncated>
		<difficult>0</difficult>
		<occluded>0</occluded>
		<bndbox>
			<xmin>468</xmin>
			<xmax>608</xmax>
			<ymin>412</ymin>
			<ymax>519</ymax>
		</bndbox>
		<polygon>
			<x1>531</x1>
			<y1>412</y1>
			<x2>530</x2>
			<y2>413</y2>
			<x3>528</x3>
			<y3>413</y3>
			<x4>527</x4>
			<y4>414</y4>
			<x5>525</x5>
			<y5>414</y5>
			<x6>524</x6>
			<y6>415</y6>
			<x7>523</x7>
			<y7>415</y7>
			<x8>522</x8>
			<y8>416</y8>
			<x9>521</x9>
			<y9>416</y9>
			<x10>520</x10>
			<y10>417</y10>
			<x11>519</x11>
			<y11>417</y11>
			<x12>518</x12>
			<y12>418</y12>
			<x13>517</x13>
			<y13>418</y13>
			<x14>516</x14>
			<y14>419</y14>
			<x15>515</x15>
			<y15>419</y15>
			<x16>514</x16>
			<y16>420</y16>
			<x17>513</x17>
			<y17>420</y17>
			<x18>512</x18>
			<y18>421</y18>
			<x19>511</x19>
			<y19>421</y19>
			<x20>509</x20>
			<y20>423</y20>
			<x21>508</x21>
			<y21>423</y21>
			<x22>507</x22>
			<y22>424</y22>
			<x23>506</x23>
			<y23>424</y23>
			<x24>505</x24>
			<y24>425</y24>
			<x25>504</x25>
			<y25>425</y25>
			<x26>503</x26>
			<y26>426</y26>
			<x27>502</x27>
			<y27>426</y27>
			<x28>501</x28>
			<y28>427</y28>
			<x29>500</x29>
			<y29>427</y29>
			<x30>498</x30>
			<y30>429</y30>
			<x31>497</x31>
			<y31>429</y31>
			<x32>495</x32>
			<y32>431</y32>
			<x33>494</x33>
			<y33>431</y33>
			<x34>492</x34>
			<y34>433</y34>
			<x35>491</x35>
			<y35>433</y35>
			<x36>489</x36>
			<y36>435</y36>
			<x37>488</x37>
			<y37>435</y37>
			<x38>486</x38>
			<y38>437</y38>
			<x39>485</x39>
			<y39>437</y39>
			<x40>483</x40>
			<y40>439</y40>
			<x41>482</x41>
			<y41>439</y41>
			<x42>480</x42>
			<y42>441</y42>
			<x43>479</x43>
			<y43>441</y43>
			<x44>477</x44>
			<y44>443</y44>
			<x45>476</x45>
			<y45>443</y45>
			<x46>472</x46>
			<y46>447</y46>
			<x47>471</x47>
			<y47>447</y47>
			<x48>469</x48>
			<y48>449</y48>
			<x49>469</x49>
			<y49>452</y49>
			<x50>468</x50>
			<y50>453</y50>
			<x51>468</x51>
			<y51>459</y51>
			<x52>467</x52>
			<y52>460</y52>
			<x53>467</x53>
			<y53>469</y53>
			<x54>468</x54>
			<y54>470</y54>
			<x55>468</x55>
			<y55>480</y55>
			<x56>469</x56>
			<y56>481</y56>
			<x57>469</x57>
			<y57>483</y57>
			<x58>470</x58>
			<y58>484</y58>
			<x59>470</x59>
			<y59>486</y59>
			<x60>471</x60>
			<y60>487</y60>
			<x61>471</x61>
			<y61>489</y61>
			<x62>472</x62>
			<y62>490</y62>
			<x63>472</x63>
			<y63>492</y63>
			<x64>473</x64>
			<y64>493</y64>
			<x65>473</x65>
			<y65>494</y65>
			<x66>476</x66>
			<y66>497</y66>
			<x67>477</x67>
			<y67>497</y67>
			<x68>481</x68>
			<y68>501</y68>
			<x69>482</x69>
			<y69>501</y69>
			<x70>485</x70>
			<y70>504</y70>
			<x71>486</x71>
			<y71>504</y71>
			<x72>487</x72>
			<y72>505</y72>
			<x73>488</x73>
			<y73>505</y73>
			<x74>489</x74>
			<y74>506</y74>
			<x75>490</x75>
			<y75>506</y75>
			<x76>491</x76>
			<y76>507</y76>
			<x77>492</x77>
			<y77>507</y77>
			<x78>492</x78>
			<y78>506</y78>
			<x79>493</x79>
			<y79>505</y79>
			<x80>493</x80>
			<y80>504</y80>
			<x81>494</x81>
			<y81>503</y81>
			<x82>495</x82>
			<y82>503</y82>
			<x83>496</x83>
			<y83>504</y83>
			<x84>496</x84>
			<y84>506</y84>
			<x85>497</x85>
			<y85>506</y85>
			<x86>498</x86>
			<y86>507</y86>
			<x87>499</x87>
			<y87>507</y87>
			<x88>500</x88>
			<y88>508</y88>
			<x89>500</x89>
			<y89>509</y89>
			<x90>499</x90>
			<y90>510</y90>
			<x91>500</x91>
			<y91>510</y91>
			<x92>501</x92>
			<y92>511</y92>
			<x93>504</x93>
			<y93>511</y93>
			<x94>505</x94>
			<y94>512</y94>
			<x95>510</x95>
			<y95>512</y95>
			<x96>511</x96>
			<y96>513</y96>
			<x97>512</x97>
			<y97>513</y97>
			<x98>515</x98>
			<y98>516</y98>
			<x99>516</x99>
			<y99>516</y99>
			<x100>518</x100>
			<y100>518</y100>
			<x101>521</x101>
			<y101>518</y101>
			<x102>522</x102>
			<y102>517</y102>
			<x103>525</x103>
			<y103>517</y103>
			<x104>528</x104>
			<y104>514</y104>
			<x105>528</x105>
			<y105>513</y105>
			<x106>529</x106>
			<y106>512</y106>
			<x107>529</x107>
			<y107>511</y107>
			<x108>530</x108>
			<y108>510</y108>
			<x109>531</x109>
			<y109>510</y109>
			<x110>532</x110>
			<y110>509</y110>
			<x111>535</x111>
			<y111>509</y111>
			<x112>539</x112>
			<y112>505</y112>
			<x113>540</x113>
			<y113>505</y113>
			<x114>546</x114>
			<y114>499</y114>
			<x115>548</x115>
			<y115>499</y115>
			<x116>549</x116>
			<y116>500</y116>
			<x117>550</x117>
			<y117>500</y117>
			<x118>552</x118>
			<y118>502</y118>
			<x119>553</x119>
			<y119>502</y119>
			<x120>554</x120>
			<y120>503</y120>
			<x121>556</x121>
			<y121>503</y121>
			<x122>557</x122>
			<y122>504</y122>
			<x123>561</x123>
			<y123>504</y123>
			<x124>562</x124>
			<y124>503</y124>
			<x125>566</x125>
			<y125>503</y125>
			<x126>568</x126>
			<y126>501</y126>
			<x127>569</x127>
			<y127>501</y127>
			<x128>572</x128>
			<y128>498</y128>
			<x129>572</x129>
			<y129>492</y129>
			<x130>571</x130>
			<y130>491</y130>
			<x131>571</x131>
			<y131>489</y131>
			<x132>570</x132>
			<y132>488</y132>
			<x133>570</x133>
			<y133>487</y133>
			<x134>569</x134>
			<y134>486</y134>
			<x135>569</x135>
			<y135>485</y135>
			<x136>568</x136>
			<y136>484</y136>
			<x137>569</x137>
			<y137>483</y137>
			<x138>569</x138>
			<y138>482</y138>
			<x139>572</x139>
			<y139>479</y139>
			<x140>572</x140>
			<y140>478</y140>
			<x141>576</x141>
			<y141>474</y141>
			<x142>576</x142>
			<y142>473</y142>
			<x143>577</x143>
			<y143>472</y143>
			<x144>577</x144>
			<y144>471</y144>
			<x145>578</x145>
			<y145>470</y145>
			<x146>578</x146>
			<y146>469</y146>
			<x147>579</x147>
			<y147>468</y147>
			<x148>579</x148>
			<y148>467</y148>
			<x149>580</x149>
			<y149>466</y149>
			<x150>580</x150>
			<y150>465</y150>
			<x151>581</x151>
			<y151>464</y151>
			<x152>582</x152>
			<y152>464</y152>
			<x153>583</x153>
			<y153>463</y153>
			<x154>585</x154>
			<y154>463</y154>
			<x155>586</x155>
			<y155>462</y155>
			<x156>587</x156>
			<y156>462</y156>
			<x157>588</x157>
			<y157>461</y157>
			<x158>590</x158>
			<y158>461</y158>
			<x159>591</x159>
			<y159>460</y159>
			<x160>592</x160>
			<y160>460</y160>
			<x161>593</x161>
			<y161>459</y161>
			<x162>594</x162>
			<y162>459</y162>
			<x163>598</x163>
			<y163>455</y163>
			<x164>599</x164>
			<y164>455</y164>
			<x165>601</x165>
			<y165>453</y165>
			<x166>601</x166>
			<y166>452</y166>
			<x167>602</x167>
			<y167>451</y167>
			<x168>602</x168>
			<y168>450</y168>
			<x169>603</x169>
			<y169>449</y169>
			<x170>603</x170>
			<y170>448</y170>
			<x171>606</x171>
			<y171>445</y171>
			<x172>606</x172>
			<y172>444</y172>
			<x173>607</x173>
			<y173>443</y173>
			<x174>607</x174>
			<y174>437</y174>
			<x175>606</x175>
			<y175>436</y175>
			<x176>606</x176>
			<y176>435</y176>
			<x177>604</x177>
			<y177>433</y177>
			<x178>603</x178>
			<y178>433</y178>
			<x179>600</x179>
			<y179>430</y179>
			<x180>599</x180>
			<y180>430</y180>
			<x181>597</x181>
			<y181>428</y181>
			<x182>596</x182>
			<y182>428</y182>
			<x183>595</x183>
			<y183>427</y183>
			<x184>594</x184>
			<y184>427</y184>
			<x185>593</x185>
			<y185>426</y185>
			<x186>592</x186>
			<y186>426</y186>
			<x187>591</x187>
			<y187>425</y187>
			<x188>590</x188>
			<y188>425</y188>
			<x189>589</x189>
			<y189>424</y189>
			<x190>588</x190>
			<y190>424</y190>
			<x191>587</x191>
			<y191>423</y191>
			<x192>586</x192>
			<y192>423</y192>
			<x193>585</x193>
			<y193>422</y193>
			<x194>584</x194>
			<y194>423</y194>
			<x195>583</x195>
			<y195>422</y195>
			<x196>582</x196>
			<y196>423</y196>
			<x197>580</x197>
			<y197>423</y197>
			<x198>579</x198>
			<y198>424</y198>
			<x199>578</x199>
			<y199>424</y199>
			<x200>575</x200>
			<y200>427</y200>
			<x201>574</x201>
			<y201>427</y201>
			<x202>570</x202>
			<y202>431</y202>
			<x203>568</x203>
			<y203>431</y203>
			<x204>567</x204>
			<y204>430</y204>
			<x205>563</x205>
			<y205>430</y205>
			<x206>562</x206>
			<y206>429</y206>
			<x207>559</x207>
			<y207>429</y207>
			<x208>558</x208>
			<y208>428</y208>
			<x209>555</x209>
			<y209>428</y209>
			<x210>554</x210>
			<y210>427</y210>
			<x211>551</x211>
			<y211>427</y211>
			<x212>550</x212>
			<y212>426</y212>
			<x213>548</x213>
			<y213>426</y213>
			<x214>547</x214>
			<y214>425</y214>
			<x215>546</x215>
			<y215>425</y215>
			<x216>545</x216>
			<y216>424</y216>
			<x217>542</x217>
			<y217>424</y217>
			<x218>541</x218>
			<y218>423</y218>
			<x219>540</x219>
			<y219>423</y219>
			<x220>539</x220>
			<y220>422</y220>
			<x221>539</x221>
			<y221>416</y221>
			<x222>535</x222>
			<y222>412</y222>
			<x223>534</x223>
			<y223>412</y223>
			<x224>533</x224>
			<y224>411</y224>
			<x225>532</x225>
			<y225>412</y225>
			<x226>531</x226>
			<y226>412</y226>
		</polygon>
	</object>
	<object>
		<name>bloodstain</name>
		<pose>Unspecified</pose>
		<truncated>0</truncated>
		<difficult>0</difficult>
		<occluded>0</occluded>
		<bndbox>
			<xmin>385</xmin>
			<xmax>423</xmax>
			<ymin>88</ymin>
			<ymax>208</ymax>
		</bndbox>
		<polygon>
			<x1>393</x1>
			<y1>88</y1>
			<x2>392</x2>
			<y2>89</y2>
			<x3>391</x3>
			<y3>89</y3>
			<x4>390</x4>
			<y4>90</y4>
			<x5>389</x5>
			<y5>90</y5>
			<x6>388</x6>
			<y6>91</y6>
			<x7>388</x7>
			<y7>92</y7>
			<x8>387</x8>
			<y8>93</y8>
			<x9>387</x9>
			<y9>94</y9>
			<x10>384</x10>
			<y10>97</y10>
			<x11>384</x11>
			<y11>104</y11>
			<x12>385</x12>
			<y12>105</y12>
			<x13>385</x13>
			<y13>114</y13>
			<x14>386</x14>
			<y14>115</y14>
			<x15>386</x15>
			<y15>124</y15>
			<x16>387</x16>
			<y16>125</y16>
			<x17>387</x17>
			<y17>126</y17>
			<x18>388</x18>
			<y18>127</y18>
			<x19>388</x19>
			<y19>152</y19>
			<x20>392</x20>
			<y20>156</y20>
			<x21>392</x21>
			<y21>157</y21>
			<x22>393</x22>
			<y22>158</y22>
			<x23>393</x23>
			<y23>159</y23>
			<x24>394</x24>
			<y24>160</y24>
			<x25>394</x25>
			<y25>161</y25>
			<x26>395</x26>
			<y26>162</y26>
			<x27>395</x27>
			<y27>164</y27>
			<x28>396</x28>
			<y28>165</y28>
			<x29>396</x29>
			<y29>168</y29>
			<x30>397</x30>
			<y30>169</y30>
			<x31>397</x31>
			<y31>172</y31>
			<x32>398</x32>
			<y32>173</y32>
			<x33>398</x33>
			<y33>176</y33>
			<x34>399</x34>
			<y34>177</y34>
			<x35>399</x35>
			<y35>181</y35>
			<x36>400</x36>
			<y36>182</y36>
			<x37>400</x37>
			<y37>185</y37>
			<x38>401</x38>
			<y38>186</y38>
			<x39>401</x39>
			<y39>189</y39>
			<x40>402</x40>
			<y40>190</y40>
			<x41>402</x41>
			<y41>194</y41>
			<x42>403</x42>
			<y42>195</y42>
			<x43>403</x43>
			<y43>200</y43>
			<x44>404</x44>
			<y44>201</y44>
			<x45>404</x45>
			<y45>204</y45>
			<x46>407</x46>
			<y46>207</y46>
			<x47>410</x47>
			<y47>207</y47>
			<x48>411</x48>
			<y48>206</y48>
			<x49>415</x49>
			<y49>206</y49>
			<x50>416</x50>
			<y50>205</y50>
			<x51>417</x51>
			<y51>205</y51>
			<x52>419</x52>
			<y52>203</y52>
			<x53>420</x53>
			<y53>203</y53>
			<x54>421</x54>
			<y54>202</y54>
			<x55>421</x55>
			<y55>198</y55>
			<x56>422</x56>
			<y56>197</y56>
			<x57>422</x57>
			<y57>190</y57>
			<x58>421</x58>
			<y58>189</y58>
			<x59>421</x59>
			<y59>180</y59>
			<x60>420</x60>
			<y60>179</y60>
			<x61>420</x61>
			<y61>174</y61>
			<x62>419</x62>
			<y62>173</y62>
			<x63>419</x63>
			<y63>172</y63>
			<x64>418</x64>
			<y64>171</y64>
			<x65>418</x65>
			<y65>170</y65>
			<x66>417</x66>
			<y66>169</y66>
			<x67>417</x67>
			<y67>168</y67>
			<x68>416</x68>
			<y68>167</y68>
			<x69>416</x69>
			<y69>166</y69>
			<x70>415</x70>
			<y70>165</y70>
			<x71>415</x71>
			<y71>164</y71>
			<x72>411</x72>
			<y72>160</y72>
			<x73>411</x73>
			<y73>159</y73>
			<x74>410</x74>
			<y74>158</y74>
			<x75>410</x75>
			<y75>156</y75>
			<x76>409</x76>
			<y76>155</y76>
			<x77>409</x77>
			<y77>153</y77>
			<x78>408</x78>
			<y78>152</y78>
			<x79>408</x79>
			<y79>150</y79>
			<x80>407</x80>
			<y80>149</y80>
			<x81>407</x81>
			<y81>148</y81>
			<x82>406</x82>
			<y82>147</y82>
			<x83>406</x83>
			<y83>146</y83>
			<x84>402</x84>
			<y84>142</y84>
			<x85>402</x85>
			<y85>141</y85>
			<x86>401</x86>
			<y86>140</y86>
			<x87>401</x87>
			<y87>137</y87>
			<x88>400</x88>
			<y88>136</y88>
			<x89>400</x89>
			<y89>133</y89>
			<x90>399</x90>
			<y90>132</y90>
			<x91>399</x91>
			<y91>129</y91>
			<x92>398</x92>
			<y92>128</y92>
			<x93>398</x93>
			<y93>125</y93>
			<x94>397</x94>
			<y94>124</y94>
			<x95>397</x95>
			<y95>123</y95>
			<x96>396</x96>
			<y96>122</y96>
			<x97>396</x97>
			<y97>107</y97>
			<x98>397</x98>
			<y98>106</y98>
			<x99>397</x99>
			<y99>88</y99>
			<x100>396</x100>
			<y100>87</y100>
			<x101>395</x101>
			<y101>88</y101>
			<x102>393</x102>
			<y102>88</y102>
		</polygon>
	</object>
	<object>
		<name>bloodstain</name>
		<pose>Unspecified</pose>
		<truncated>0</truncated>
		<difficult>0</difficult>
		<occluded>0</occluded>
		<bndbox>
			<xmin>471</xmin>
			<xmax>495</xmax>
			<ymin>309</ymin>
			<ymax>334</ymax>
		</bndbox>
		<polygon>
			<x1>472</x1>
			<y1>309</y1>
			<x2>471</x2>
			<y2>310</y2>
			<x3>471</x3>
			<y3>311</y3>
			<x4>470</x4>
			<y4>312</y4>
			<x5>470</x5>
			<y5>321</y5>
			<x6>471</x6>
			<y6>322</y6>
			<x7>471</x7>
			<y7>323</y7>
			<x8>472</x8>
			<y8>324</y8>
			<x9>472</x9>
			<y9>325</y9>
			<x10>474</x10>
			<y10>327</y10>
			<x11>474</x11>
			<y11>328</y11>
			<x12>478</x12>
			<y12>332</y12>
			<x13>479</x13>
			<y13>332</y13>
			<x14>480</x14>
			<y14>333</y14>
			<x15>491</x15>
			<y15>333</y15>
			<x16>492</x16>
			<y16>332</y16>
			<x17>492</x17>
			<y17>331</y17>
			<x18>493</x18>
			<y18>330</y18>
			<x19>493</x19>
			<y19>329</y19>
			<x20>494</x20>
			<y20>328</y20>
			<x21>494</x21>
			<y21>321</y21>
			<x22>493</x22>
			<y22>320</y22>
			<x23>493</x23>
			<y23>319</y23>
			<x24>485</x24>
			<y24>311</y24>
			<x25>484</x25>
			<y25>311</y25>
			<x26>483</x26>
			<y26>310</y26>
			<x27>482</x27>
			<y27>310</y27>
			<x28>481</x28>
			<y28>309</y28>
			<x29>478</x29>
			<y29>309</y29>
			<x30>477</x30>
			<y30>308</y30>
			<x31>476</x31>
			<y31>308</y31>
			<x32>475</x32>
			<y32>309</y32>
			<x33>474</x33>
			<y33>308</y33>
			<x34>473</x34>
			<y34>309</y34>
			<x35>472</x35>
			<y35>309</y35>
		</polygon>
	</object>
	<object>
		<name>bloodstain</name>
		<pose>Unspecified</pose>
		<truncated>0</truncated>
		<difficult>0</difficult>
		<occluded>0</occluded>
		<bndbox>
			<xmin>395</xmin>
			<xmax>414</xmax>
			<ymin>308</ymin>
			<ymax>328</ymax>
		</bndbox>
		<polygon>
			<x1>395</x1>
			<y1>308</y1>
			<x2>395</x2>
			<y2>309</y2>
			<x3>394</x3>
			<y3>310</y3>
			<x4>394</x4>
			<y4>318</y4>
			<x5>395</x5>
			<y5>319</y5>
			<x6>395</x6>
			<y6>321</y6>
			<x7>396</x7>
			<y7>322</y7>
			<x8>396</x8>
			<y8>323</y8>
			<x9>398</x9>
			<y9>325</y9>
			<x10>399</x10>
			<y10>325</y10>
			<x11>400</x11>
			<y11>326</y11>
			<x12>401</x12>
			<y12>326</y12>
			<x13>402</x13>
			<y13>327</y13>
			<x14>405</x14>
			<y14>327</y14>
			<x15>406</x15>
			<y15>326</y15>
			<x16>408</x16>
			<y16>326</y16>
			<x17>409</x17>
			<y17>325</y17>
			<x18>410</x18>
			<y18>325</y18>
			<x19>411</x19>
			<y19>324</y19>
			<x20>412</x20>
			<y20>324</y20>
			<x21>412</x21>
			<y21>322</y21>
			<x22>413</x22>
			<y22>321</y22>
			<x23>413</x23>
			<y23>319</y23>
			<x24>412</x24>
			<y24>318</y24>
			<x25>412</x25>
			<y25>317</y25>
			<x26>411</x26>
			<y26>316</y26>
			<x27>411</x27>
			<y27>315</y27>
			<x28>410</x28>
			<y28>314</y28>
			<x29>410</x29>
			<y29>313</y29>
			<x30>408</x30>
			<y30>311</y30>
			<x31>407</x31>
			<y31>311</y31>
			<x32>406</x32>
			<y32>310</y32>
			<x33>405</x33>
			<y33>310</y33>
			<x34>404</x34>
			<y34>309</y34>
			<x35>403</x35>
			<y35>309</y35>
			<x36>402</x36>
			<y36>308</y36>
			<x37>399</x37>
			<y37>308</y37>
			<x38>398</x38>
			<y38>307</y38>
			<x39>397</x39>
			<y39>307</y39>
			<x40>396</x40>
			<y40>308</y40>
			<x41>395</x41>
			<y41>308</y41>
		</polygon>
	</object>
	<object>
		<name>bloodstain</name>
		<pose>Unspecified</pose>
		<truncated>0</truncated>
		<difficult>0</difficult>
		<occluded>0</occluded>
		<bndbox>
			<xmin>592</xmin>
			<xmax>669</xmax>
			<ymin>712</ymin>
			<ymax>758</ymax>
		</bndbox>
		<polygon>
			<x1>601</x1>
			<y1>712</y1>
			<x2>600</x2>
			<y2>713</y2>
			<x3>599</x3>
			<y3>713</y3>
			<x4>597</x4>
			<y4>715</y4>
			<x5>597</x5>
			<y5>716</y5>
			<x6>594</x6>
			<y6>719</y6>
			<x7>594</x7>
			<y7>720</y7>
			<x8>593</x8>
			<y8>721</y8>
			<x9>593</x9>
			<y9>722</y9>
			<x10>592</x10>
			<y10>723</y10>
			<x11>592</x11>
			<y11>724</y11>
			<x12>591</x12>
			<y12>725</y12>
			<x13>591</x13>
			<y13>731</y13>
			<x14>592</x14>
			<y14>732</y14>
			<x15>592</x15>
			<y15>733</y15>
			<x16>594</x16>
			<y16>735</y16>
			<x17>594</x17>
			<y17>736</y17>
			<x18>597</x18>
			<y18>739</y18>
			<x19>597</x19>
			<y19>740</y19>
			<x20>599</x20>
			<y20>742</y20>
			<x21>600</x21>
			<y21>742</y21>
			<x22>601</x22>
			<y22>743</y22>
			<x23>602</x23>
			<y23>743</y23>
			<x24>603</x24>
			<y24>744</y24>
			<x25>605</x25>
			<y25>744</y25>
			<x26>606</x26>
			<y26>745</y26>
			<x27>608</x27>
			<y27>745</y27>
			<x28>609</x28>
			<y28>746</y28>
			<x29>611</x29>
			<y29>746</y29>
			<x30>612</x30>
			<y30>747</y30>
			<x31>614</x31>
			<y31>747</y31>
			<x32>615</x32>
			<y32>748</y32>
			<x33>616</x33>
			<y33>748</y33>
			<x34>617</x34>
			<y34>747</y34>
			<x35>618</x35>
			<y35>747</y35>
			<x36>619</x36>
			<y36>746</y36>
			<x37>623</x37>
			<y37>746</y37>
			<x38>625</x38>
			<y38>748</y38>
			<x39>626</x39>
			<y39>748</y39>
			<x40>627</x40>
			<y40>749</y40>
			<x41>627</x41>
			<y41>750</y41>
			<x42>628</x42>
			<y42>750</y42>
			<x43>629</x43>
			<y43>749</y43>
			<x44>631</x44>
			<y44>749</y44>
			<x45>632</x45>
			<y45>748</y45>
			<x46>633</x46>
			<y46>748</y46>
			<x47>634</x47>
			<y47>747</y47>
			<x48>636</x48>
			<y48>749</y48>
			<x49>636</x49>
			<y49>751</y49>
			<x50>637</x50>
			<y50>752</y50>
			<x51>638</x51>
			<y51>752</y51>
			<x52>639</x52>
			<y52>753</y52>
			<x53>640</x53>
			<y53>753</y53>
			<x54>642</x54>
			<y54>755</y54>
			<x55>643</x55>
			<y55>755</y55>
			<x56>644</x56>
			<y56>756</y56>
			<x57>645</x57>
			<y57>756</y57>
			<x58>646</x58>
			<y58>757</y58>
			<x59>652</x59>
			<y59>757</y59>
			<x60>653</x60>
			<y60>756</y60>
			<x61>656</x61>
			<y61>756</y61>
			<x62>657</x62>
			<y62>755</y62>
			<x63>658</x63>
			<y63>755</y63>
			<x64>659</x64>
			<y64>754</y64>
			<x65>660</x65>
			<y65>754</y65>
			<x66>661</x66>
			<y66>753</y66>
			<x67>661</x67>
			<y67>752</y67>
			<x68>666</x68>
			<y68>747</y68>
			<x69>666</x69>
			<y69>744</y69>
			<x70>667</x70>
			<y70>743</y70>
			<x71>667</x71>
			<y71>732</y71>
			<x72>668</x72>
			<y72>731</y72>
			<x73>667</x73>
			<y73>731</y73>
			<x74>666</x74>
			<y74>730</y74>
			<x75>665</x75>
			<y75>730</y75>
			<x76>662</x76>
			<y76>727</y76>
			<x77>661</x77>
			<y77>727</y77>
			<x78>654</x78>
			<y78>720</y78>
			<x79>651</x79>
			<y79>720</y79>
			<x80>650</x80>
			<y80>719</y80>
			<x81>649</x81>
			<y81>719</y81>
			<x82>648</x82>
			<y82>720</y82>
			<x83>647</x83>
			<y83>719</y83>
			<x84>646</x84>
			<y84>720</y84>
			<x85>644</x85>
			<y85>720</y85>
			<x86>643</x86>
			<y86>721</y86>
			<x87>642</x87>
			<y87>721</y87>
			<x88>641</x88>
			<y88>722</y88>
			<x89>640</x89>
			<y89>722</y89>
			<x90>637</x90>
			<y90>725</y90>
			<x91>636</x91>
			<y91>725</y91>
			<x92>635</x92>
			<y92>724</y92>
			<x93>634</x93>
			<y93>724</y93>
			<x94>630</x94>
			<y94>720</y94>
			<x95>630</x95>
			<y95>719</y95>
			<x96>629</x96>
			<y96>718</y96>
			<x97>629</x97>
			<y97>717</y97>
			<x98>628</x98>
			<y98>716</y98>
			<x99>627</x99>
			<y99>716</y99>
			<x100>626</x100>
			<y100>715</y100>
			<x101>625</x101>
			<y101>715</y101>
			<x102>624</x102>
			<y102>714</y102>
			<x103>623</x103>
			<y103>714</y103>
			<x104>622</x104>
			<y104>713</y104>
			<x105>621</x105>
			<y105>713</y105>
			<x106>620</x106>
			<y106>712</y106>
			<x107>617</x107>
			<y107>712</y107>
			<x108>616</x108>
			<y108>711</y108>
			<x109>614</x109>
			<y109>711</y109>
			<x110>613</x110>
			<y110>712</y110>
			<x111>612</x111>
			<y111>711</y111>
			<x112>605</x112>
			<y112>711</y112>
			<x113>604</x113>
			<y113>712</y113>
			<x114>603</x114>
			<y114>711</y114>
			<x115>602</x115>
			<y115>712</y115>
			<x116>601</x116>
			<y116>712</y116>
		</polygon>
	</object>
	<object>
		<name>bloodstain</name>
		<pose>Unspecified</pose>
		<truncated>0</truncated>
		<difficult>0</difficult>
		<occluded>0</occluded>
		<bndbox>
			<xmin>539</xmin>
			<xmax>598</xmax>
			<ymin>739</ymin>
			<ymax>766</ymax>
		</bndbox>
		<polygon>
			<x1>543</x1>
			<y1>739</y1>
			<x2>542</x2>
			<y2>740</y2>
			<x3>541</x3>
			<y3>740</y3>
			<x4>539</x4>
			<y4>742</y4>
			<x5>539</x5>
			<y5>743</y5>
			<x6>538</x6>
			<y6>744</y6>
			<x7>538</x7>
			<y7>752</y7>
			<x8>539</x8>
			<y8>753</y8>
			<x9>539</x9>
			<y9>754</y9>
			<x10>543</x10>
			<y10>758</y10>
			<x11>543</x11>
			<y11>759</y11>
			<x12>545</x12>
			<y12>761</y12>
			<x13>546</x13>
			<y13>761</y13>
			<x14>547</x14>
			<y14>762</y14>
			<x15>549</x15>
			<y15>762</y15>
			<x16>550</x16>
			<y16>763</y16>
			<x17>551</x17>
			<y17>763</y17>
			<x18>552</x18>
			<y18>764</y18>
			<x19>555</x19>
			<y19>764</y19>
			<x20>556</x20>
			<y20>765</y20>
			<x21>560</x21>
			<y21>765</y21>
			<x22>561</x22>
			<y22>764</y22>
			<x23>563</x23>
			<y23>764</y23>
			<x24>565</x24>
			<y24>762</y24>
			<x25>565</x25>
			<y25>761</y25>
			<x26>566</x26>
			<y26>760</y26>
			<x27>566</x27>
			<y27>759</y27>
			<x28>567</x28>
			<y28>758</y28>
			<x29>567</x29>
			<y29>757</y29>
			<x30>569</x30>
			<y30>755</y30>
			<x31>597</x31>
			<y31>755</y31>
			<x32>597</x32>
			<y32>754</y32>
			<x33>596</x33>
			<y33>753</y33>
			<x34>596</x34>
			<y34>752</y34>
			<x35>593</x35>
			<y35>749</y35>
			<x36>592</x36>
			<y36>749</y36>
			<x37>591</x37>
			<y37>748</y37>
			<x38>590</x38>
			<y38>749</y38>
			<x39>584</x39>
			<y39>749</y39>
			<x40>583</x40>
			<y40>750</y40>
			<x41>573</x41>
			<y41>750</y41>
			<x42>572</x42>
			<y42>751</y42>
			<x43>571</x43>
			<y43>750</y43>
			<x44>569</x44>
			<y44>750</y44>
			<x45>568</x45>
			<y45>749</y45>
			<x46>568</x46>
			<y46>747</y46>
			<x47>567</x47>
			<y47>746</y47>
			<x48>567</x48>
			<y48>745</y48>
			<x49>565</x49>
			<y49>743</y49>
			<x50>564</x50>
			<y50>743</y50>
			<x51>563</x51>
			<y51>742</y51>
			<x52>562</x52>
			<y52>742</y52>
			<x53>561</x53>
			<y53>741</y53>
			<x54>559</x54>
			<y54>741</y54>
			<x55>558</x55>
			<y55>740</y55>
			<x56>555</x56>
			<y56>740</y56>
			<x57>554</x57>
			<y57>739</y57>
			<x58>551</x58>
			<y58>739</y58>
			<x59>550</x59>
			<y59>738</y59>
			<x60>549</x60>
			<y60>739</y60>
			<x61>548</x61>
			<y61>738</y61>
			<x62>547</x62>
			<y62>738</y62>
			<x63>546</x63>
			<y63>739</y63>
			<x64>543</x64>
			<y64>739</y64>
		</polygon>
	</object>
	<object>
		<name>bloodstain</name>
		<pose>Unspecified</pose>
		<truncated>0</truncated>
		<difficult>0</difficult>
		<occluded>0</occluded>
		<bndbox>
			<xmin>446</xmin>
			<xmax>498</xmax>
			<ymin>791</ymin>
			<ymax>839</ymax>
		</bndbox>
		<polygon>
			<x1>461</x1>
			<y1>791</y1>
			<x2>460</x2>
			<y2>792</y2>
			<x3>459</x3>
			<y3>792</y3>
			<x4>458</x4>
			<y4>793</y4>
			<x5>457</x5>
			<y5>793</y5>
			<x6>456</x6>
			<y6>794</y6>
			<x7>455</x7>
			<y7>794</y7>
			<x8>453</x8>
			<y8>796</y8>
			<x9>453</x9>
			<y9>797</y9>
			<x10>451</x10>
			<y10>799</y10>
			<x11>451</x11>
			<y11>800</y11>
			<x12>449</x12>
			<y12>802</y12>
			<x13>449</x13>
			<y13>803</y13>
			<x14>448</x14>
			<y14>804</y14>
			<x15>448</x15>
			<y15>805</y15>
			<x16>447</x16>
			<y16>806</y16>
			<x17>447</x17>
			<y17>809</y17>
			<x18>446</x18>
			<y18>810</y18>
			<x19>446</x19>
			<y19>813</y19>
			<x20>445</x20>
			<y20>814</y20>
			<x21>445</x21>
			<y21>816</y21>
			<x22>446</x22>
			<y22>817</y22>
			<x23>446</x23>
			<y23>819</y23>
			<x24>447</x24>
			<y24>820</y24>
			<x25>447</x25>
			<y25>823</y25>
			<x26>448</x26>
			<y26>824</y26>
			<x27>448</x27>
			<y27>825</y27>
			<x28>450</x28>
			<y28>827</y28>
			<x29>450</x29>
			<y29>828</y29>
			<x30>455</x30>
			<y30>833</y30>
			<x31>456</x31>
			<y31>833</y31>
			<x32>459</x32>
			<y32>836</y32>
			<x33>460</x33>
			<y33>836</y33>
			<x34>461</x34>
			<y34>837</y34>
			<x35>464</x35>
			<y35>837</y35>
			<x36>465</x36>
			<y36>838</y36>
			<x37>470</x37>
			<y37>838</y37>
			<x38>471</x38>
			<y38>837</y38>
			<x39>477</x39>
			<y39>837</y39>
			<x40>478</x40>
			<y40>836</y40>
			<x41>482</x41>
			<y41>836</y41>
			<x42>483</x42>
			<y42>835</y42>
			<x43>484</x43>
			<y43>835</y43>
			<x44>485</x44>
			<y44>834</y44>
			<x45>486</x45>
			<y45>834</y45>
			<x46>492</x46>
			<y46>828</y46>
			<x47>493</x47>
			<y47>828</y47>
			<x48>495</x48>
			<y48>826</y48>
			<x49>495</x49>
			<y49>825</y49>
			<x50>496</x50>
			<y50>824</y50>
			<x51>496</x51>
			<y51>823</y51>
			<x52>497</x52>
			<y52>822</y52>
			<x53>497</x53>
			<y53>809</y53>
			<x54>496</x54>
			<y54>808</y54>
			<x55>496</x55>
			<y55>807</y55>
			<x56>495</x56>
			<y56>806</y56>
			<x57>495</x57>
			<y57>805</y57>
			<x58>494</x58>
			<y58>804</y58>
			<x59>494</x59>
			<y59>803</y59>
			<x60>492</x60>
			<y60>801</y60>
			<x61>492</x61>
			<y61>800</y61>
			<x62>491</x62>
			<y62>799</y62>
			<x63>491</x63>
			<y63>798</y63>
			<x64>490</x64>
			<y64>797</y64>
			<x65>489</x65>
			<y65>797</y65>
			<x66>488</x66>
			<y66>796</y66>
			<x67>487</x67>
			<y67>796</y67>
			<x68>486</x68>
			<y68>795</y68>
			<x69>485</x69>
			<y69>795</y69>
			<x70>484</x70>
			<y70>794</y70>
			<x71>483</x71>
			<y71>794</y71>
			<x72>482</x72>
			<y72>793</y72>
			<x73>481</x73>
			<y73>793</y73>
			<x74>480</x74>
			<y74>792</y74>
			<x75>479</x75>
			<y75>792</y75>
			<x76>478</x76>
			<y76>791</y76>
			<x77>474</x77>
			<y77>791</y77>
			<x78>473</x78>
			<y78>790</y78>
			<x79>471</x79>
			<y79>790</y79>
			<x80>470</x80>
			<y80>791</y80>
			<x81>469</x81>
			<y81>790</y81>
			<x82>464</x82>
			<y82>790</y82>
			<x83>463</x83>
			<y83>791</y83>
			<x84>461</x84>
			<y84>791</y84>
		</polygon>
	</object>
	<object>
		<name>bloodstain</name>
		<pose>Unspecified</pose>
		<truncated>0</truncated>
		<difficult>0</difficult>
		<occluded>0</occluded>
		<bndbox>
			<xmin>890</xmin>
			<xmax>921</xmax>
			<ymin>751</ymin>
			<ymax>781</ymax>
		</bndbox>
		<polygon>
			<x1>898</x1>
			<y1>751</y1>
			<x2>894</x2>
			<y2>755</y2>
			<x3>894</x3>
			<y3>756</y3>
			<x4>893</x4>
			<y4>757</y4>
			<x5>893</x5>
			<y5>758</y5>
			<x6>892</x6>
			<y6>759</y6>
			<x7>892</x7>
			<y7>762</y7>
			<x8>891</x8>
			<y8>763</y8>
			<x9>891</x9>
			<y9>766</y9>
			<x10>890</x10>
			<y10>767</y10>
			<x11>890</x11>
			<y11>768</y11>
			<x12>889</x12>
			<y12>769</y12>
			<x13>889</x13>
			<y13>770</y13>
			<x14>890</x14>
			<y14>771</y14>
			<x15>890</x15>
			<y15>772</y15>
			<x16>893</x16>
			<y16>775</y16>
			<x17>893</x17>
			<y17>776</y17>
			<x18>894</x18>
			<y18>777</y18>
			<x19>894</x19>
			<y19>778</y19>
			<x20>896</x20>
			<y20>780</y20>
			<x21>909</x21>
			<y21>780</y21>
			<x22>910</x22>
			<y22>779</y22>
			<x23>911</x23>
			<y23>779</y23>
			<x24>912</x24>
			<y24>778</y24>
			<x25>913</x25>
			<y25>778</y25>
			<x26>914</x26>
			<y26>777</y26>
			<x27>915</x27>
			<y27>777</y27>
			<x28>917</x28>
			<y28>775</y28>
			<x29>917</x29>
			<y29>774</y29>
			<x30>919</x30>
			<y30>772</y30>
			<x31>919</x31>
			<y31>771</y31>
			<x32>920</x32>
			<y32>770</y32>
			<x33>920</x33>
			<y33>761</y33>
			<x34>919</x34>
			<y34>760</y34>
			<x35>919</x35>
			<y35>758</y35>
			<x36>912</x36>
			<y36>751</y36>
			<x37>910</x37>
			<y37>751</y37>
			<x38>909</x38>
			<y38>750</y38>
			<x39>907</x39>
			<y39>750</y39>
			<x40>906</x40>
			<y40>751</y40>
			<x41>905</x41>
			<y41>750</y41>
			<x42>901</x42>
			<y42>750</y42>
			<x43>900</x43>
			<y43>751</y43>
			<x44>898</x44>
			<y44>751</y44>
		</polygon>
	</object>
</annotation>
