<annotation>
	<folder></folder>
	<filename>abrasions-75-_jpg.rf.3c7c8beb8ae5d0f4d919a5bdf44550f5.jpg</filename>
	<path>abrasions-75-_jpg.rf.3c7c8beb8ae5d0f4d919a5bdf44550f5.jpg</path>
	<source>
		<database>roboflow.com</database>
	</source>
	<size>
		<width>640</width>
		<height>640</height>
		<depth>3</depth>
	</size>
	<segmented>0</segmented>
	<object>
		<name>abrasions</name>
		<pose>Unspecified</pose>
		<truncated>0</truncated>
		<difficult>0</difficult>
		<occluded>0</occluded>
		<bndbox>
			<xmin>230</xmin>
			<xmax>434</xmax>
			<ymin>275</ymin>
			<ymax>408</ymax>
		</bndbox>
	</object>
</annotation>
