<annotation verified="yes">
	<folder>train</folder>
	<filename>D4VXCF8DYZTL_jpg.rf.c8b72f676bc4540f43218d3e54056683.jpg</filename>
	<path>C:\Applied_project_Vita_M\Object detection\Images\Equipment_with_XML\syringe.v2i.voc (2)\train\D4VXCF8DYZTL_jpg.rf.c8b72f676bc4540f43218d3e54056683.jpg</path>
	<source>
		<database>Unknown</database>
	</source>
	<size>
		<width>640</width>
		<height>640</height>
		<depth>3</depth>
	</size>
	<segmented>0</segmented>
	<object>
		<name>Dangerous</name>
		<pose>Unspecified</pose>
		<truncated>1</truncated>
		<difficult>0</difficult>
		<bndbox>
			<xmin>7</xmin>
			<ymin>1</ymin>
			<xmax>629</xmax>
			<ymax>641</ymax>
		</bndbox>
	</object>
</annotation>
