<annotation>
	<folder></folder>
	<filename>GOPR0802-2-_mp4-0230_jpg.rf.e83c29c1c0a70e5fb1f572a246a9e584.jpg</filename>
	<path>GOPR0802-2-_mp4-0230_jpg.rf.e83c29c1c0a70e5fb1f572a246a9e584.jpg</path>
	<source>
		<database>roboflow.com</database>
	</source>
	<size>
		<width>640</width>
		<height>640</height>
		<depth>3</depth>
	</size>
	<segmented>0</segmented>
	<object>
		<name>Tourniquet</name>
		<pose>Unspecified</pose>
		<truncated>0</truncated>
		<difficult>0</difficult>
		<occluded>0</occluded>
		<bndbox>
			<xmin>174</xmin>
			<xmax>342</xmax>
			<ymin>1</ymin>
			<ymax>127</ymax>
		</bndbox>
	</object>
	<metadata>
	</metadata>
</annotation>
