<annotation>
	<folder></folder>
	<filename>GOPR0802-2-_mp4-0375_jpg.rf.3465bc5f9a17382b60ff3600dc407ffb.jpg</filename>
	<path>GOPR0802-2-_mp4-0375_jpg.rf.3465bc5f9a17382b60ff3600dc407ffb.jpg</path>
	<source>
		<database>roboflow.com</database>
	</source>
	<size>
		<width>640</width>
		<height>640</height>
		<depth>3</depth>
	</size>
	<segmented>0</segmented>
	<object>
		<name>Tourniquet</name>
		<pose>Unspecified</pose>
		<truncated>0</truncated>
		<difficult>0</difficult>
		<occluded>0</occluded>
		<bndbox>
			<xmin>200</xmin>
			<xmax>268</xmax>
			<ymin>71</ymin>
			<ymax>256</ymax>
		</bndbox>
	</object>
	<metadata>
	</metadata>
</annotation>
